Workbook
Name IQ_CH: 110000
Name IQ_CQ: 5000
Name IQ_CY: 10000
Name IQ_DAILY: 500000
Name IQ_FH: 100000
Name IQ_FQ: 500
Name IQ_FY: 1000
Name IQ_LTM: 2000
Name IQ_MONTH: 15000
Name IQ_NTM: 6000
Name IQ_WEEK: 50000
Name IQ_YTD: 3000

Sheet Cover>

Sheet ControlSheet
B2: Mrs Sector Foods
B3: Control Sheet
F4: Current Case | G4: 1
F8: Actual | G8: Explicit Forecast Period
B9: In INR crores unless started otherwise | F9: 2023 | G9: =F9+1 -> 2024 | H9: =G9+1 -> 2025 | I9: =H9+1 -> 2026 | J9: =I9+1 -> 2027 | K9: =J9+1 -> 2028
A11: # | B11: Sales Assumptions
B13: Cereals
B15: Price/Box - yoy % Growth
B16: Management Case | G16: 0.03 | H16: 0.03 | I16: 0.03 | J16: 0.03 | K16: 0.03
B17: Best Case | G17: 0.04 | H17: 0.04 | I17: 0.04 | J17: 0.04 | K17: 0.04
B18: Down Case | G18: 0.02 | H18: 0.02 | I18: 0.02 | J18: 0.02 | K18: 0.02
B19: ="Current Case - "&CHOOSE($G$4,B16,B17,B18) -> Current Case - Management Case | G19: =CHOOSE($G$4,G16,G17,G18) -> 0.03 | H19: =CHOOSE($G$4,H16,H17,H18) -> 0.03 | I19: =CHOOSE($G$4,I16,I17,I18) -> 0.03 | J19: =CHOOSE($G$4,J16,J17,J18) -> 0.03 | K19: =CHOOSE($G$4,K16,K17,K18) -> 0.03
B21: Number of Boxes Sold - yoy % Growth
B22: Management Case | G22: 0.08 | H22: 0.08 | I22: 0.08 | J22: 0.07 | K22: 0.07
B23: Best Case | G23: 0.09 | H23: 0.09 | I23: 0.09 | J23: 0.09 | K23: 0.09
B24: Down Case | G24: 0.07 | H24: 0.07 | I24: 0.07 | J24: 0.07 | K24: 0.07
B25: ="Current Case - "&CHOOSE($G$4,B22,B23,B24) -> Current Case - Management Case | G25: =CHOOSE($G$4,G22,G23,G24) -> 0.08 | H25: =CHOOSE($G$4,H22,H23,H24) -> 0.08 | I25: =CHOOSE($G$4,I22,I23,I24) -> 0.08 | J25: =CHOOSE($G$4,J22,J23,J24) -> 0.07 | K25: =CHOOSE($G$4,K22,K23,K24) -> 0.07
B27: Pickle
B29: Price/Sachets- yoy % Growth
B30: Management Case | G30: 0.02 | H30: 0.02 | I30: 0.02 | J30: 0.02 | K30: 0.02
B31: Best Case | G31: 0.03 | H31: 0.03 | I31: 0.03 | J31: 0.03 | K31: 0.03
B32: Down Case | G32: 0.01 | H32: 0.01 | I32: 0.01 | J32: 0.01 | K32: 0.01
B33: ="Current Case - "&CHOOSE($G$4,B30,B31,B32) -> Current Case - Management Case | G33: =CHOOSE($G$4,G30,G31,G32) -> 0.02 | H33: =CHOOSE($G$4,H30,H31,H32) -> 0.02 | I33: =CHOOSE($G$4,I30,I31,I32) -> 0.02 | J33: =CHOOSE($G$4,J30,J31,J32) -> 0.02 | K33: =CHOOSE($G$4,K30,K31,K32) -> 0.02
B35: Number of Sachets Sold - yoy % Growth
B36: Management Case | G36: 0.07 | H36: 0.07 | I36: 0.07 | J36: 0.05 | K36: 0.05
B37: Best Case | G37: 0.08 | H37: 0.08 | I37: 0.08 | J37: 0.08 | K37: 0.08
B38: Down Case | G38: 0.06 | H38: 0.06 | I38: 0.06 | J38: 0.06 | K38: 0.06
B39: ="Current Case - "&CHOOSE($G$4,B36,B37,B38) -> Current Case - Management Case | G39: =CHOOSE($G$4,G36,G37,G38) -> 0.07 | H39: =CHOOSE($G$4,H36,H37,H38) -> 0.07 | I39: =CHOOSE($G$4,I36,I37,I38) -> 0.07 | J39: =CHOOSE($G$4,J36,J37,J38) -> 0.05 | K39: =CHOOSE($G$4,K36,K37,K38) -> 0.05
B41: Sauces
B43: Price/Sachets- yoy % Growth
B44: Management Case | G44: 0.01 | H44: 0.01 | I44: 0.01 | J44: 0.01 | K44: 0.01
B45: Best Case | G45: 0.02 | H45: 0.02 | I45: 0.02 | J45: 0.02 | K45: 0.02
B46: Down Case | G46: 0 | H46: 0 | I46: 0 | J46: 0 | K46: 0
B47: ="Current Case - "&CHOOSE($G$4,B44,B45,B46) -> Current Case - Management Case | G47: =CHOOSE($G$4,G44,G45,G46) -> 0.01 | H47: =CHOOSE($G$4,H44,H45,H46) -> 0.01 | I47: =CHOOSE($G$4,I44,I45,I46) -> 0.01 | J47: =CHOOSE($G$4,J44,J45,J46) -> 0.01 | K47: =CHOOSE($G$4,K44,K45,K46) -> 0.01
B49: Number of Sachets Sold - yoy % Growth
B50: Management Case | G50: 0.05 | H50: 0.05 | I50: 0.03 | J50: 0.03 | K50: 0.03
B51: Best Case | G51: 0.06 | H51: 0.06 | I51: 0.06 | J51: 0.06 | K51: 0.06
B52: Down Case | G52: 0.04 | H52: 0.04 | I52: 0.04 | J52: 0.04 | K52: 0.04
B53: ="Current Case - "&CHOOSE($G$4,B50,B51,B52) -> Current Case - Management Case | G53: =CHOOSE($G$4,G50,G51,G52) -> 0.05 | H53: =CHOOSE($G$4,H50,H51,H52) -> 0.05 | I53: =CHOOSE($G$4,I50,I51,I52) -> 0.03 | J53: =CHOOSE($G$4,J50,J51,J52) -> 0.03 | K53: =CHOOSE($G$4,K50,K51,K52) -> 0.03
A55: # | B55: COGS Assumptions
B57: Cereals
B59: Raw Material Cost - yoy % Growth
B60: Management Case | G60: 0 | H60: 0 | I60: 0 | J60: 0 | K60: 0
B61: Best Case | G61: 0.01 | H61: 0.01 | I61: 0.01 | J61: 0.01 | K61: 0.01
B62: Down Case | G62: 0.02 | H62: 0.02 | I62: 0.02 | J62: 0.02 | K62: 0.02
B63: ="Current Case - "&CHOOSE($G$4,B60,B61,B62) -> Current Case - Management Case | G63: =CHOOSE($G$4,G60,G61,G62) -> 0 | H63: =CHOOSE($G$4,H60,H61,H62) -> 0 | I63: =CHOOSE($G$4,I60,I61,I62) -> 0 | J63: =CHOOSE($G$4,J60,J61,J62) -> 0 | K63: =CHOOSE($G$4,K60,K61,K62) -> 0
B65: Labour Cost - yoy % Growth
B66: Management Case | G66: 0 | H66: 0 | I66: 0 | J66: 0 | K66: 0
B67: Best Case | G67: 0.01 | H67: 0.01 | I67: 0.01 | J67: 0.01 | K67: 0.01
B68: Down Case | G68: 0.02 | H68: 0.02 | I68: 0.02 | J68: 0.02 | K68: 0.02
B69: ="Current Case - "&CHOOSE($G$4,B66,B67,B68) -> Current Case - Management Case | G69: =CHOOSE($G$4,G66,G67,G68) -> 0 | H69: =CHOOSE($G$4,H66,H67,H68) -> 0 | I69: =CHOOSE($G$4,I66,I67,I68) -> 0 | J69: =CHOOSE($G$4,J66,J67,J68) -> 0 | K69: =CHOOSE($G$4,K66,K67,K68) -> 0
B71: Packaging Cost - yoy % Growth
B72: Management Case | G72: 0 | H72: 0 | I72: 0 | J72: 0 | K72: 0
B73: Best Case | G73: 0.01 | H73: 0.01 | I73: 0.01 | J73: 0.01 | K73: 0.01
B74: Down Case | G74: 0.02 | H74: 0.02 | I74: 0.02 | J74: 0.02 | K74: 0.02
B75: ="Current Case - "&CHOOSE($G$4,B72,B73,B74) -> Current Case - Management Case | G75: =CHOOSE($G$4,G72,G73,G74) -> 0 | H75: =CHOOSE($G$4,H72,H73,H74) -> 0 | I75: =CHOOSE($G$4,I72,I73,I74) -> 0 | J75: =CHOOSE($G$4,J72,J73,J74) -> 0 | K75: =CHOOSE($G$4,K72,K73,K74) -> 0
B77: Delivery Cost - yoy % Growth
B78: Management Case | G78: 0 | H78: 0 | I78: 0 | J78: 0 | K78: 0
B79: Best Case | G79: 0.01 | H79: 0.01 | I79: 0.01 | J79: 0.01 | K79: 0.01
B80: Down Case | G80: 0.02 | H80: 0.02 | I80: 0.02 | J80: 0.02 | K80: 0.02
B81: ="Current Case - "&CHOOSE($G$4,B78,B79,B80) -> Current Case - Management Case | G81: =CHOOSE($G$4,G78,G79,G80) -> 0 | H81: =CHOOSE($G$4,H78,H79,H80) -> 0 | I81: =CHOOSE($G$4,I78,I79,I80) -> 0 | J81: =CHOOSE($G$4,J78,J79,J80) -> 0 | K81: =CHOOSE($G$4,K78,K79,K80) -> 0
B84: Pickle
B86: Raw Material Cost - yoy % Growth
B87: Management Case | G87: 0 | H87: 0 | I87: 0 | J87: 0 | K87: 0
B88: Best Case | G88: 0.01 | H88: 0.01 | I88: 0.01 | J88: 0.01 | K88: 0.01
B89: Down Case | G89: 0.02 | H89: 0.02 | I89: 0.02 | J89: 0.02 | K89: 0.02
B90: ="Current Case - "&CHOOSE($G$4,B87,B88,B89) -> Current Case - Management Case | G90: =CHOOSE($G$4,G87,G88,G89) -> 0 | H90: =CHOOSE($G$4,H87,H88,H89) -> 0 | I90: =CHOOSE($G$4,I87,I88,I89) -> 0 | J90: =CHOOSE($G$4,J87,J88,J89) -> 0 | K90: =CHOOSE($G$4,K87,K88,K89) -> 0
B92: Labour Cost - yoy % Growth
B93: Management Case | G93: 0 | H93: 0 | I93: 0 | J93: 0 | K93: 0
B94: Best Case | G94: 0.01 | H94: 0.01 | I94: 0.01 | J94: 0.01 | K94: 0.01
B95: Down Case | G95: 0.02 | H95: 0.02 | I95: 0.02 | J95: 0.02 | K95: 0.02
B96: ="Current Case - "&CHOOSE($G$4,B93,B94,B95) -> Current Case - Management Case | G96: =CHOOSE($G$4,G93,G94,G95) -> 0 | H96: =CHOOSE($G$4,H93,H94,H95) -> 0 | I96: =CHOOSE($G$4,I93,I94,I95) -> 0 | J96: =CHOOSE($G$4,J93,J94,J95) -> 0 | K96: =CHOOSE($G$4,K93,K94,K95) -> 0
B98: Packaging Cost - yoy % Growth
B99: Management Case | G99: 0 | H99: 0 | I99: 0 | J99: 0 | K99: 0
B100: Best Case | G100: 0.01 | H100: 0.01 | I100: 0.01 | J100: 0.01 | K100: 0.01
B101: Down Case | G101: 0.02 | H101: 0.02 | I101: 0.02 | J101: 0.02 | K101: 0.02
B102: ="Current Case - "&CHOOSE($G$4,B99,B100,B101) -> Current Case - Management Case | G102: =CHOOSE($G$4,G99,G100,G101) -> 0 | H102: =CHOOSE($G$4,H99,H100,H101) -> 0 | I102: =CHOOSE($G$4,I99,I100,I101) -> 0 | J102: =CHOOSE($G$4,J99,J100,J101) -> 0 | K102: =CHOOSE($G$4,K99,K100,K101) -> 0
B104: Delivery Cost - yoy % Growth
B105: Management Case | G105: 0 | H105: 0 | I105: 0 | J105: 0 | K105: 0
B106: Best Case | G106: 0.01 | H106: 0.01 | I106: 0.01 | J106: 0.01 | K106: 0.01
B107: Down Case | G107: 0.02 | H107: 0.02 | I107: 0.02 | J107: 0.02 | K107: 0.02
B108: ="Current Case - "&CHOOSE($G$4,B105,B106,B107) -> Current Case - Management Case | G108: =CHOOSE($G$4,G105,G106,G107) -> 0 | H108: =CHOOSE($G$4,H105,H106,H107) -> 0 | I108: =CHOOSE($G$4,I105,I106,I107) -> 0 | J108: =CHOOSE($G$4,J105,J106,J107) -> 0 | K108: =CHOOSE($G$4,K105,K106,K107) -> 0
B110: Sauces
B112: Raw Material Cost - yoy % Growth
B113: Management Case | G113: 0 | H113: 0 | I113: 0 | J113: 0 | K113: 0
B114: Best Case | G114: 0.01 | H114: 0.01 | I114: 0.01 | J114: 0.01 | K114: 0.01
B115: Down Case | G115: 0.02 | H115: 0.02 | I115: 0.02 | J115: 0.02 | K115: 0.02
B116: ="Current Case - "&CHOOSE($G$4,B113,B114,B115) -> Current Case - Management Case | G116: =CHOOSE($G$4,G113,G114,G115) -> 0 | H116: =CHOOSE($G$4,H113,H114,H115) -> 0 | I116: =CHOOSE($G$4,I113,I114,I115) -> 0 | J116: =CHOOSE($G$4,J113,J114,J115) -> 0 | K116: =CHOOSE($G$4,K113,K114,K115) -> 0
B118: Labour Cost - yoy % Growth
B119: Management Case | G119: 0 | H119: 0 | I119: 0 | J119: 0 | K119: 0
B120: Best Case | G120: 0.01 | H120: 0.01 | I120: 0.01 | J120: 0.01 | K120: 0.01
B121: Down Case | G121: 0.02 | H121: 0.02 | I121: 0.02 | J121: 0.02 | K121: 0.02
B122: ="Current Case - "&CHOOSE($G$4,B119,B120,B121) -> Current Case - Management Case | G122: =CHOOSE($G$4,G119,G120,G121) -> 0 | H122: =CHOOSE($G$4,H119,H120,H121) -> 0 | I122: =CHOOSE($G$4,I119,I120,I121) -> 0 | J122: =CHOOSE($G$4,J119,J120,J121) -> 0 | K122: =CHOOSE($G$4,K119,K120,K121) -> 0
B124: Packaging Cost - yoy % Growth
B125: Management Case | G125: 0 | H125: 0 | I125: 0 | J125: 0 | K125: 0
B126: Best Case | G126: 0.01 | H126: 0.01 | I126: 0.01 | J126: 0.01 | K126: 0.01
B127: Down Case | G127: 0.02 | H127: 0.02 | I127: 0.02 | J127: 0.02 | K127: 0.02
B128: ="Current Case - "&CHOOSE($G$4,B125,B126,B127) -> Current Case - Management Case | G128: =CHOOSE($G$4,G125,G126,G127) -> 0 | H128: =CHOOSE($G$4,H125,H126,H127) -> 0 | I128: =CHOOSE($G$4,I125,I126,I127) -> 0 | J128: =CHOOSE($G$4,J125,J126,J127) -> 0 | K128: =CHOOSE($G$4,K125,K126,K127) -> 0
B130: Delivery Cost - yoy % Growth
B131: Management Case | G131: 0 | H131: 0 | I131: 0 | J131: 0 | K131: 0
...

Sheet Schedules
B2: Mrs Sector Foods
B3: Control Sheet
E4: Current Case | F4: 1
E8: Actual | F8: Explicit Forecast Period
B9: In INR crores unless started otherwise | E9: 2023 | F9: =E9+1 -> 2024 | G9: =F9+1 -> 2025 | H9: =G9+1 -> 2026 | I9: =H9+1 -> 2027 | J9: =I9+1 -> 2028
A11: # | B11: Sales Schedules
B13: Cereals
B15: Price/Box | E15: 150 | F15: =E15*(1+F19) -> 154.5 | G15: =F15*(1+G19) -> 159.135 | H15: =G15*(1+H19) -> 163.90905 | I15: =H15*(1+I19) -> 168.82632 | J15: =I15*(1+J19) -> 173.89111
B16: Number of boxes Sold (in crs) | E16: 279 | F16: =E16*(1+F20) -> 301.32 | G16: =F16*(1+G20) -> 325.4256 | H16: =G16*(1+H20) -> 351.45965 | I16: =H16*(1+I20) -> 376.06182 | J16: =I16*(1+J20) -> 402.38615
B17: Total Sales - Cereals | E17: =E16*E15 -> 41850 | F17: =F16*F15 -> 46553.94 | G17: =G16*G15 -> 51786.603 | H17: =H16*H15 -> 57607.417 | I17: =I16*I15 -> 63489.134 | J17: =J16*J15 -> 69971.375
B19: Price growth % y-o-y | F19: =ControlSheet!G19 -> 0.03 | G19: =ControlSheet!G19 -> 0.03 | H19: =ControlSheet!H19 -> 0.03 | I19: =ControlSheet!I19 -> 0.03 | J19: =ControlSheet!J19 -> 0.03
B20: Volume growth % y-o-y | F20: =ControlSheet!G25 -> 0.08 | G20: =ControlSheet!H25 -> 0.08 | H20: =ControlSheet!I25 -> 0.08 | I20: =ControlSheet!J25 -> 0.07 | J20: =ControlSheet!K25 -> 0.07
B21: Total Sales - Cereals growth % y-o-y | F21: =F17/E17-1 -> 0.1124 | G21: =G17/F17-1 -> 0.1124 | H21: =H17/G17-1 -> 0.1124 | I21: =I17/H17-1 -> 0.1021 | J21: =J17/I17-1 -> 0.1021
B23: Pickle
B25: Price/Box | E25: 50 | F25: =E25*(1+F29) -> 51 | G25: =F25*(1+G29) -> 52.02 | H25: =G25*(1+H29) -> 53.0604 | I25: =H25*(1+I29) -> 54.121608 | J25: =I25*(1+J29) -> 55.20404
B26: Number of boxes Sold (in crs) | E26: 217 | F26: =E26*(1+F30) -> 232.19 | G26: =F26*(1+G30) -> 248.4433 | H26: =G26*(1+H30) -> 265.83433 | I26: =H26*(1+I30) -> 279.12605 | J26: =I26*(1+J30) -> 293.08235
B27: Total Sales - Pickle | E27: =E26*E25 -> 10850 | F27: =F26*F25 -> 11841.69 | G27: =G26*G25 -> 12924.02 | H27: =H26*H25 -> 14105.276 | I27: =I26*I25 -> 15106.751 | J27: =J26*J25 -> 16179.33
B29: Price growth % y-o-y | F29: =ControlSheet!G33 -> 0.02 | G29: =ControlSheet!H33 -> 0.02 | H29: =ControlSheet!I33 -> 0.02 | I29: =ControlSheet!J33 -> 0.02 | J29: =ControlSheet!K33 -> 0.02
B30: Volume growth % y-o-y | F30: =ControlSheet!G39 -> 0.07 | G30: =ControlSheet!H39 -> 0.07 | H30: =ControlSheet!I39 -> 0.07 | I30: =ControlSheet!J39 -> 0.05 | J30: =ControlSheet!K39 -> 0.05
B31: Total Sales - Pickle growth % y-o-y | F31: =F27/E27-1 -> 0.0914 | G31: =G27/F27-1 -> 0.0914 | H31: =H27/G27-1 -> 0.0914 | I31: =I27/H27-1 -> 0.071 | J31: =J27/I27-1 -> 0.071
B33: Sauces
B35: Price/Box | E35: 30 | F35: =E35*(1+F39) -> 30.3 | G35: =F35*(1+G39) -> 30.603 | H35: =G35*(1+H39) -> 30.90903 | I35: =H35*(1+I39) -> 31.21812 | J35: =I35*(1+J39) -> 31.530302
B36: Number of boxes Sold (in crs) | E36: 177 | F36: =E36*(1+F40) -> 185.85 | G36: =F36*(1+G40) -> 195.1425 | H36: =G36*(1+H40) -> 200.99678 | I36: =H36*(1+I40) -> 207.02668 | J36: =I36*(1+J40) -> 213.23748
B37: Total Sales - Sauces | E37: =E36*E35 -> 5310 | F37: =F36*F35 -> 5631.255 | G37: =G36*G35 -> 5971.9459 | H37: =H36*H35 -> 6212.6153 | I37: =I36*I35 -> 6462.9837 | J37: =J36*J35 -> 6723.442
B39: Price growth % y-o-y | F39: =ControlSheet!G47 -> 0.01 | G39: =ControlSheet!H47 -> 0.01 | H39: =ControlSheet!I47 -> 0.01 | I39: =ControlSheet!J47 -> 0.01 | J39: =ControlSheet!K47 -> 0.01
B40: Volume growth % y-o-y | F40: =ControlSheet!G53 -> 0.05 | G40: =ControlSheet!H53 -> 0.05 | H40: =ControlSheet!I53 -> 0.03 | I40: =ControlSheet!J53 -> 0.03 | J40: =ControlSheet!K53 -> 0.03
B41: Total Sales - Sauces growth % y-o-y | F41: =F37/E37-1 -> 0.0605 | G41: =G37/F37-1 -> 0.0605 | H41: =H37/G37-1 -> 0.0403 | I41: =I37/H37-1 -> 0.0403 | J41: =J37/I37-1 -> 0.0403
B44: Total Sales | E44: =E37+E27+E17 -> 58010 | F44: =F37+F27+F17 -> 64026.885 | G44: =G37+G27+G17 -> 70682.569 | H44: =H37+H27+H17 -> 77925.308 | I44: =I37+I27+I17 -> 85058.869 | J44: =J37+J27+J17 -> 92874.147
B45: Total Sales - growth % y-o-y | F45: =F44/E44-1 -> 0.10372151 | G45: =G44/F44-1 -> 0.1039514 | H45: =H44/G44-1 -> 0.10246853 | I45: =I44/H44-1 -> 0.091543562 | J45: =J44/I44-1 -> 0.091880815
A48: # | B48: COGS Schedules
B50: Cereals
B52: Total Boxes Sold | E52: =E16 -> 279 | F52: =F16 -> 301.32 | G52: =G16 -> 325.4256 | H52: =H16 -> 351.45965 | I52: =I16 -> 376.06182 | J52: =J16 -> 402.38615
B54: Raw Material Cost/Box | E54: 27.5 | F54: =E54*(1+F68) -> 27.5 | G54: =F54*(1+G68) -> 27.5 | H54: =G54*(1+H68) -> 27.5 | I54: =H54*(1+I68) -> 27.5 | J54: =I54*(1+J68) -> 27.5
B55: Total Raw Material Cost | E55: =E54*E$52 -> 7672.5 | F55: =F54*F$52 -> 8286.3 | G55: =G54*G$52 -> 8949.204 | H55: =H54*H$52 -> 9665.1403 | I55: =I54*I$52 -> 10341.7 | J55: =J52*J54 -> 11065.619
B57: Labour Cost/Box | E57: 10 | F57: =E57*(1+F69) -> 10 | G57: =F57*(1+G69) -> 10 | H57: =G57*(1+H69) -> 10 | I57: =H57*(1+I69) -> 10 | J57: =I57*(1+J69) -> 10
B58: Total Labour Cost | E58: =E57*E$52 -> 2790 | F58: =F57*F$52 -> 3013.2 | G58: =G57*G$52 -> 3254.256 | H58: =H57*H$52 -> 3514.5965 | I58: =I57*I$52 -> 3760.6182 | J58: =J57*J$52 -> 4023.8615
B60: Packaging Cost/Box | E60: 12.5 | F60: =E60*(1+F70) -> 12.5 | G60: =F60*(1+G70) -> 12.5 | H60: =G60*(1+H70) -> 12.5 | I60: =H60*(1+I70) -> 12.5 | J60: =I60*(1+J70) -> 12.5
B61: Total Packaging Cost | E61: =E60*E$52 -> 3487.5 | F61: =F60*F$52 -> 3766.5 | G61: =G60*G$52 -> 4067.82 | H61: =H60*H$52 -> 4393.2456 | I61: =I60*I$52 -> 4700.7728 | J61: =J60*J$52 -> 5029.8269
B63: Delivery Cost/Box | E63: 8 | F63: =E63*(1+F71) -> 8 | G63: =F63*(1+G71) -> 8 | H63: =G63*(1+H71) -> 8 | I63: =H63*(1+I71) -> 8 | J63: =I63*(1+J71) -> 8
B64: Total Delivery Cost | E64: =E63*E$52 -> 2232 | F64: =F63*F$52 -> 2410.56 | G64: =G63*G$52 -> 2603.4048 | H64: =H63*H$52 -> 2811.6772 | I64: =I63*I$52 -> 3008.4946 | J64: =J63*J$52 -> 3219.0892
B66: Total COGS - Cereals | E66: =E64+E61+E58+E55 -> 16182 | F66: =F64+F61+F58+F55 -> 17476.56 | G66: =G64+G61+G58+G55 -> 18874.685 | H66: =H64+H61+H58+H55 -> 20384.66 | I66: =I64+I61+I58+I55 -> 21811.586 | J66: =J64+J61+J58+J55 -> 23338.397
B68: Raw Material Cost - Growth % yoy | F68: =ControlSheet!G63 -> 0 | G68: =ControlSheet!H63 -> 0 | H68: =ControlSheet!I63 -> 0 | I68: =ControlSheet!J63 -> 0 | J68: =ControlSheet!K63 -> 0
B69: Labour Cost - Growth % yoy | F69: =ControlSheet!G69 -> 0 | G69: =ControlSheet!H69 -> 0 | H69: =ControlSheet!I69 -> 0 | I69: =ControlSheet!J69 -> 0 | J69: =ControlSheet!K69 -> 0
B70: Packaging Cost - Growth % yoy | F70: =ControlSheet!G75 -> 0 | G70: =ControlSheet!H75 -> 0 | H70: =ControlSheet!I75 -> 0 | I70: =ControlSheet!J75 -> 0 | J70: =ControlSheet!K75 -> 0
B71: Delivery Cost - Growth % yoy | F71: =ControlSheet!G81 -> 0 | G71: =ControlSheet!H81 -> 0 | H71: =ControlSheet!I81 -> 0 | I71: =ControlSheet!J81 -> 0 | J71: =ControlSheet!K81 -> 0
B72: Total Cost - % of Cereals Sales | E72: =E66/E17 -> 0.38666667 | F72: =F66/F17 -> 0.37540453 | G72: =G66/G17 -> 0.36447042 | H72: =H66/H17 -> 0.35385477 | I72: =I66/I17 -> 0.34354833 | J72: =J66/J17 -> 0.33354206
B73: Gross Margin - Cereals | E73: =100%-E72 -> 0.61333333 | F73: =100%-F72 -> 0.62459547 | G73: =100%-G72 -> 0.63552958 | H73: =100%-H72 -> 0.64614523 | I73: =100%-I72 -> 0.65645167 | J73: =100%-J72 -> 0.66645794
B75: Pickle
B77: Total Sachets Sold | E77: =E26 -> 217 | F77: =F26 -> 232.19 | G77: =G26 -> 248.4433 | H77: =H26 -> 265.83433 | I77: =I26 -> 279.12605 | J77: =J26 -> 293.08235
B79: Raw Material Cost/Sachets | E79: 7.5 | F79: =E79*(1+F93) -> 7.5 | G79: =F79*(1+G93) -> 7.5 | H79: =G79*(1+H93) -> 7.5 | I79: =H79*(1+I93) -> 7.5 | J79: =I79*(1+J93) -> 7.5
B80: Total Raw Material Cost | E80: =E79*E77 -> 1627.5 | F80: =F79*F77 -> 1741.425 | G80: =G79*G77 -> 1863.3248 | H80: =H79*H77 -> 1993.7575 | I80: =I79*I77 -> 2093.4454 | J80: =J79*J77 -> 2198.1176
B82: Labour Cost/Sachets | E82: 2.5 | F82: =E82*(1+F94) -> 2.5 | G82: =F82*(1+G94) -> 2.5 | H82: =G82*(1+H94) -> 2.5 | I82: =H82*(1+I94) -> 2.5 | J82: =I82*(1+J94) -> 2.5
B83: Total Labour Cost | E83: =E82*E77 -> 542.5 | F83: =F82*F77 -> 580.475 | G83: =G82*G77 -> 621.10825 | H83: =H82*H77 -> 664.58583 | I83: =I82*I77 -> 697.81512 | J83: =J82*J77 -> 732.70587
B85: Packaging Cost/Sachets | E85: 20 | F85: =E85*(1+F95) -> 20 | G85: =F85*(1+G95) -> 20 | H85: =G85*(1+H95) -> 20 | I85: =H85*(1+I95) -> 20 | J85: =I85*(1+J95) -> 20
B86: Total Packaging Cost | E86: =E85*E77 -> 4340 | F86: =F85*F77 -> 4643.8 | G86: =G85*G77 -> 4968.866 | H86: =H85*H77 -> 5316.6866 | I86: =I85*I77 -> 5582.521 | J86: =J85*J77 -> 5861.647
B88: Delivery Cost/Sachets | E88: 5 | F88: =E88*(1+F96) -> 5 | G88: =F88*(1+G96) -> 5 | H88: =G88*(1+H96) -> 5 | I88: =H88*(1+I96) -> 5 | J88: =I88*(1+J96) -> 5
B89: Total Delivery Cost | E89: =E88*E77 -> 1085 | F89: =F88*F77 -> 1160.95 | G89: =G88*G77 -> 1242.2165 | H89: =H88*H77 -> 1329.1717 | I89: =I88*I77 -> 1395.6302 | J89: =J88*J77 -> 1465.4117
B91: Total COGS - Pickles | E91: =E89+E86+E83+E80 -> 7595 | F91: =F89+F86+F83+F80 -> 8126.65 | G91: =G89+G86+G83+G80 -> 8695.5155 | H91: =H89+H86+H83+H80 -> 9304.2016 | I91: =I89+I86+I83+I80 -> 9769.4117 | J91: =J89+J86+J83+J80 -> 10257.882
B93: Raw Material Cost - Growth % yoy | F93: =ControlSheet!G90 -> 0 | G93: =ControlSheet!H90 -> 0 | H93: =ControlSheet!I90 -> 0 | I93: =ControlSheet!J90 -> 0 | J93: =ControlSheet!K90 -> 0
B94: Labour Cost - Growth % yoy | F94: =ControlSheet!G96 -> 0 | G94: =ControlSheet!H96 -> 0 | H94: =ControlSheet!I96 -> 0 | I94: =ControlSheet!J96 -> 0 | J94: =ControlSheet!K96 -> 0
B95: Packaging Cost - Growth % yoy | F95: =ControlSheet!G102 -> 0 | G95: =ControlSheet!H102 -> 0 | H95: =ControlSheet!I102 -> 0 | I95: =ControlSheet!J102 -> 0 | J95: =ControlSheet!K102 -> 0
B96: Delivery Cost - Growth % yoy | F96: =ControlSheet!G108 -> 0 | G96: =ControlSheet!H108 -> 0 | H96: =ControlSheet!I108 -> 0 | I96: =ControlSheet!J108 -> 0 | J96: =ControlSheet!K108 -> 0
B97: Total Cost - % of Cereals Sales | E97: =E91/E27 -> 0.7 | F97: =F91/F27 -> 0.68627451 | G97: =G91/G27 -> 0.67281815 | H97: =H91/H27 -> 0.65962563 | I97: =I91/I27 -> 0.6466918 | J97: =J91/J27 -> 0.63401157
B98: Gross Margin - Cereals | E98: =100%-E97 -> 0.3 | F98: =100%-F97 -> 0.31372549 | G98: =100%-G97 -> 0.32718185 | H98: =100%-H97 -> 0.34037437 | I98: =100%-I97 -> 0.3533082 | J98: =100%-J97 -> 0.36598843
B100: Sauces
B102: Total Sachets Sold | E102: =E36 -> 177 | F102: =F36 -> 185.85 | G102: =G36 -> 195.1425 | H102: =H36 -> 200.99678 | I102: =I36 -> 207.02668 | J102: =J36 -> 213.23748
B104: Raw Material Cost/Sachets | E104: 5 | F104: =E104*(1+F120) -> 5 | G104: =F104*(1+G120) -> 5 | H104: =G104*(1+H120) -> 5 | I104: =H104*(1+I120) -> 5 | J104: =I104*(1+J120) -> 5
B105: Total Raw Material Cost | E105: =E104*E102 -> 885 | F105: =F104*F102 -> 929.25 | G105: =G104*G102 -> 975.7125 | H105: =H104*H102 -> 1004.9839 | I105: =I104*I102 -> 1035.1334 | J105: =J104*J102 -> 1066.1874
B107: Labour Cost/Sachets | E107: 2.5 | F107: =E107*(1+F121) -> 2.5 | G107: =F107*(1+G121) -> 2.5 | H107: =G107*(1+H121) -> 2.5 | I107: =H107*(1+I121) -> 2.5 | J107: =I107*(1+J121) -> 2.5
B108: Total Labour Cost | E108: =E107*E102 -> 442.5 | F108: =F107*F102 -> 464.625 | G108: =G107*G102 -> 487.85625 | H108: =H107*H102 -> 502.49194 | I108: =I107*I102 -> 517.5667 | J108: =J107*J102 -> 533.0937
B110: Packaging Cost/Sachets | E110: 2.5 | F110: =E110*(1+F122) -> 2.5 | G110: =F110*(1+G122) -> 2.5 | H110: =G110*(1+H122) -> 2.5 | I110: =H110*(1+I122) -> 2.5 | J110: =I110*(1+J122) -> 2.5
B111: Total Packaging Cost | E111: =E110*E102 -> 442.5 | F111: =F110*F102 -> 464.625 | G111: =G110*G102 -> 487.85625 | H111: =H110*H102 -> 502.49194 | I111: =I110*I102 -> 517.5667 | J111: =J110*J102 -> 533.0937
B113: Delivery Cost/Sachets | E113: 10 | F113: =E113*(1+F123) -> 10 | G113: =F113*(1+G123) -> 10 | H113: =G113*(1+H123) -> 10 | I113: =H113*(1+I123) -> 10 | J113: =I113*(1+J123) -> 10
B114: Total Delivery Cost | E114: =E113*E102 -> 1770 | F114: =F113*F102 -> 1858.5 | G114: =G113*G102 -> 1951.425 | H114: =H113*H102 -> 2009.9678 | I114: =I113*I102 -> 2070.2668 | J114: =J113*J102 -> 2132.3748
B116: Total Spoilage Allowance | E116: =E37*E124 -> 796.5 | F116: =F37*F124 -> 844.68825 | G116: =G37*G124 -> 895.79189 | H116: =H37*H124 -> 931.8923 | I116: =I37*I124 -> 969.44756 | J116: =J37*J124 -> 1008.5163
B118: Total COGS - Sauces | E118: =E116+E114+E111+E108+E105 -> 4336.5 | F118: =F116+F114+F111+F108+F105 -> 4561.6883 | G118: =G116+G114+G111+G108+G105 -> 4798.6419 | H118: =H116+H114+H111+H108+H105 -> 4951.8278 | I118: =I116+I114+I111+I108+I105 -> 5109.9811 | J118: =J116+J114+J111+J108+J105 -> 5273.2659
B120: Raw Material Cost - Growth % yoy | F120: =ControlSheet!G116 -> 0 | G120: =ControlSheet!H116 -> 0 | H120: =ControlSheet!I116 -> 0 | I120: =ControlSheet!J116 -> 0 | J120: =ControlSheet!K116 -> 0
B121: Labour Cost - Growth % yoy | F121: =ControlSheet!G122 -> 0 | G121: =ControlSheet!H122 -> 0 | H121: =ControlSheet!I122 -> 0 | I121: =ControlSheet!J122 -> 0 | J121: =ControlSheet!K122 -> 0
B122: Packaging Cost - Growth % yoy | F122: =ControlSheet!G128 -> 0 | G122: =ControlSheet!H128 -> 0 | H122: =ControlSheet!I128 -> 0 | I122: =ControlSheet!J128 -> 0 | J122: =ControlSheet!K128 -> 0
B123: Delivery Cost - Growth % yoy | F123: =ControlSheet!G134 -> 0 | G123: =ControlSheet!H134 -> 0 | H123: =ControlSheet!I134 -> 0 | I123: =ControlSheet!J134 -> 0 | J123: =ControlSheet!K134 -> 0
B124: Spoilage Allowance % Sales | E124: 0.15 | F124: =ControlSheet!G140 -> 0.15 | G124: =ControlSheet!H140 -> 0.15 | H124: =ControlSheet!I140 -> 0.15 | I124: =ControlSheet!J140 -> 0.15 | J124: =ControlSheet!K140 -> 0.15
B125: Total Cost - % of Cereals Sales | E125: =E118/E37 -> 0.81666667 | F125: =F118/F37 -> 0.81006601 | G125: =G118/G37 -> 0.8035307 | H125: =H118/H37 -> 0.7970601 | I125: =I118/I37 -> 0.79065356 | J125: =J118/J37 -> 0.78431046
B126: Gross Margin - Cereals | E126: =100%-E125 -> 0.18333333 | F126: =100%-F125 -> 0.18993399 | G126: =100%-G125 -> 0.1964693 | H126: =100%-H125 -> 0.2029399 | I126: =100%-I125 -> 0.20934644 | J126: =100%-J125 -> 0.21568954
B128: Totall COGS - All Products | E128: =E66+E91+E118 -> 28113.5 | F128: =F66+F91+F118 -> 30164.898 | G128: =G66+G91+G118 -> 32368.842 | H128: =H66+H91+H118 -> 34640.689 | I128: =I66+I91+I118 -> 36690.979 | J128: =J66+J91+J118 -> 38869.545
B129: Totall COGS - All Products % Sales | E129: =E128/E44 -> 0.48463196 | F129: =F128/F44 -> 0.47112862 | G129: =G128/G44 -> 0.4579466 | H129: =H128/H44 -> 0.44453708 | I129: =I128/I44 -> 0.43135982 | J129: =J128/J44 -> 0.41851846
B130: Total Gross Margin (All Products) | E130: =1-E129 -> 0.51536804 | F130: =1-F129 -> 0.52887138 | G130: =1-G129 -> 0.5420534 | H130: =1-H129 -> 0.55546292 | I130: =1-I129 -> 0.56864018 | J130: =1-J129 -> 0.58148154
A132: # | B132: SG&A (Excluding Depreciation & Interest Expenses) Schedules
B134: Rent - Current Factories
B135: Bangalore Factories Rent | E135: 980 | F135: =E135*(1+F139) -> 980 | G135: =F135*(1+G139) -> 980 | H135: =G135*(1+H139) -> 980 | I135: =H135*(1+I139) -> 980 | J135: =I135*(1+J139) -> 980
B136: Noida Factory Rent | E136: 294 | F136: =E136*(1+F140) -> 294 | G136: =F136*(1+G140) -> 294 | H136: =G136*(1+H140) -> 294 | I136: =H136*(1+I140) -> 294 | J136: =I136*(1+J140) -> 294
B137: Total Rent - Current Factory | E137: =E136+E135 -> 1274 | F137: =F136+F135 -> 1274 | G137: =G136+G135 -> 1274 | H137: =H136+H135 -> 1274 | I137: =I136+I135 -> 1274 | J137: =J136+J135 -> 1274
B139: Bangalore Factories Rent - Growth % y-o-y | F139: =ControlSheet!G150 -> 0 | G139: =ControlSheet!H150 -> 0 | H139: =ControlSheet!I150 -> 0 | I139: =ControlSheet!J150 -> 0 | J139: =ControlSheet!K150 -> 0
B140: Noida Factories Rent - Growth % y-o-y | F140: =ControlSheet!G156 -> 0 | G140: =ControlSheet!H156 -> 0 | H140: =ControlSheet!I156 -> 0 | I140: =ControlSheet!J156 -> 0 | J140: =ControlSheet!K156 -> 0
B141: Total Current Factory Rent - Growth % y-o-y | F141: =F137/E137-1 -> 0 | G141: =G137/F137-1 -> 0 | H141: =H137/G137-1 -> 0 | I141: =I137/H137-1 -> 0 | J141: =J137/I137-1 -> 0
B142: Total Current Factory Rent - % Sales | E142: =E137/E44 -> 0.021961731 | F142: =F137/F44 -> 0.019897891 | G142: =G137/G44 -> 0.018024246 | H142: =H137/H44 -> 0.016348989 | I142: =I137/I44 -> 0.014977862 | J142: =J137/J44 -> 0.013717488
B144: Rent - New Factories
B146: Bangalore Factory - Share in Sales | C146: Total Area (in Sq ft) | D146: 39200 | E146: =E$44/($D$146+$D$147)*$D146 -> 41435.714 | F146: =F$44/($D$146+$D$147)*$D146 -> 45733.489 | G146: =G$44/($D$146+$D$147)*$D146 -> 50487.549 | H146: =H$44/($D$146+$D$147)*$D146 -> 55660.935 | I146: =I$44/($D$146+$D$147)*$D146 -> 60756.335 | J146: =J$44/($D$146+$D$147)*$D146 -> 66338.676
B147: Noida Factory - Share in Sales | C147: Total Area (in Sq ft) | D147: 15680 | E147: =E$44/($D$146+$D$147)*$D147 -> 16574.286 | F147: =F$44/($D$146+$D$147)*$D147 -> 18293.396 | G147: =G$44/($D$146+$D$147)*$D147 -> 20195.02 | H147: =H$44/($D$146+$D$147)*$D147 -> 22264.374 | I147: =I$44/($D$146+$D$147)*$D147 -> 24302.534 | J147: =J$44/($D$146+$D$147)*$D147 -> 26535.47
B149: Bangalore Factory - Max Capacity | C149: Current Capacity | D149: 0.85 | E149: =$E$146/$D$149 -> 48747.899 | F149: =$E$146/$D$149 -> 48747.899 | G149: =$E$146/$D$149 -> 48747.899 | H149: =$E$146/$D$149 -> 48747.899 | I149: =$E$146/$D$149 -> 48747.899 | J149: =$E$146/$D$149 -> 48747.899
B150: Noida Factory - Max Capacity | C150: Current Capacity | D150: 0.85 | E150: =$E$147/$D$150 -> 19499.16 | F150: =$E$147/$D$150 -> 19499.16 | G150: =$E$147/$D$150 -> 19499.16 | H150: =$E$147/$D$150 -> 19499.16 | I150: =$E$147/$D$150 -> 19499.16 | J150: =$E$147/$D$150 -> 19499.16
...

Sheet 3 Statement Model
B2: Mrs Sector Foods
B3: 3 Statement Model
F4: Current Case | G4: 1
I5: =G49/G62 -> 0.091450866
M7: CAGR
D8: Actual | G8: Explicit Forecast Period | M8: 5 Year | N8: 3 Year
B9: In INR crores unless started otherwise | D9: 2021 | E9: =D9+1 -> 2022 | F9: =E9+1 -> 2023 | G9: =F9+1 -> 2024 | H9: =G9+1 -> 2025 | I9: =H9+1 -> 2026 | J9: =I9+1 -> 2027 | K9: =J9+1 -> 2028
A11: # | B11: Income Statement
B13: Revenue | D13: =INDEX(' Income Statement'!$E$8:$G$27,MATCH('3 Statement Model'!$B13,' Income Statement'!$B$8:$B$27,0),MATCH('3 Statement Model'!D$9,' Income Statement'!$E$6:$G$6,0)) -> 47325.572 | E13: =INDEX(' Income Statement'!$E$8:$G$27,MATCH('3 Statement Model'!$B13,' Income Statement'!$B$8:$B$27,0),MATCH('3 Statement Model'!E$9,' Income Statement'!$E$6:$G$6,0)) -> 52562.986 | F13: =INDEX(' Income Statement'!$E$8:$G$27,MATCH('3 Statement Model'!$B13,' Income Statement'!$B$8:$B$27,0),MATCH('3 Statement Model'!F$9,' Income Statement'!$E$6:$G$6,0)) -> 58055.612 | G13: =Schedules!F44 -> 64026.885 | H13: =Schedules!G44 -> 70682.569 | I13: =Schedules!H44 -> 77925.308 | J13: =Schedules!I44 -> 85058.869 | K13: =Schedules!J44 -> 92874.147 | M13: =_xlfn.RRI($K$9-$F$9,F13,K13) -> 0.098525459 | N13: =_xlfn.RRI($K$9-$H$9,H13,K13) -> 0.095285916
B14: Less: Cost of Goods Sold | D14: =INDEX(' Income Statement'!$E$8:$G$27,MATCH('3 Statement Model'!$B14,' Income Statement'!$B$8:$B$27,0),MATCH('3 Statement Model'!D$9,' Income Statement'!$E$6:$G$6,0)) -> -24230.696 | E14: =INDEX(' Income Statement'!$E$8:$G$27,MATCH('3 Statement Model'!$B14,' Income Statement'!$B$8:$B$27,0),MATCH('3 Statement Model'!E$9,' Income Statement'!$E$6:$G$6,0)) -> -26556.942 | F14: =INDEX(' Income Statement'!$E$8:$G$27,MATCH('3 Statement Model'!$B14,' Income Statement'!$B$8:$B$27,0),MATCH('3 Statement Model'!F$9,' Income Statement'!$E$6:$G$6,0)) -> -28130.39 | G14: =Schedules!F128*-1 -> -30164.898 | H14: =Schedules!G128*-1 -> -32368.842 | I14: =Schedules!H128*-1 -> -34640.689 | J14: =Schedules!I128*-1 -> -36690.979 | K14: =Schedules!J128*-1 -> -38869.545 | M14: =_xlfn.RRI($K$9-$F$9,F14,K14) -> 0.066809168 | N14: =_xlfn.RRI($K$9-$H$9,H14,K14) -> 0.062904135
B15: Gross Profit | D15: =SUM(D13:D14) -> 23094.876 | E15: =SUM(E13:E14) -> 26006.044 | F15: =SUM(F13:F14) -> 29925.221 | G15: =SUM(G13:G14) -> 33861.987 | H15: =SUM(H13:H14) -> 38313.727 | I15: =SUM(I13:I14) -> 43284.619 | J15: =SUM(J13:J14) -> 48367.89 | K15: =SUM(K13:K14) -> 54004.602 | M15: =_xlfn.RRI($K$9-$F$9,F15,K15) -> 0.12532685 | N15: =_xlfn.RRI($K$9-$H$9,H15,K15) -> 0.12122332
B17: Less: SG&A Expenses (Excluding Depreciation & Interest)
B18: Administrative Costs | D18: =INDEX(' Income Statement'!$E$8:$G$27,MATCH('3 Statement Model'!$B18,' Income Statement'!$B$8:$B$27,0),MATCH('3 Statement Model'!D$9,' Income Statement'!$E$6:$G$6,0)) -> -285.278 | E18: =INDEX(' Income Statement'!$E$8:$G$27,MATCH('3 Statement Model'!$B18,' Income Statement'!$B$8:$B$27,0),MATCH('3 Statement Model'!E$9,' Income Statement'!$E$6:$G$6,0)) -> -314.776 | F18: =INDEX(' Income Statement'!$E$8:$G$27,MATCH('3 Statement Model'!$B18,' Income Statement'!$B$8:$B$27,0),MATCH('3 Statement Model'!F$9,' Income Statement'!$E$6:$G$6,0)) -> -347.6648 | G18: =Schedules!F172*-1 -> -640.26885 | H18: =Schedules!G172*-1 -> -706.82569 | I18: =Schedules!H172*-1 -> -779.25308 | J18: =Schedules!I172*-1 -> -850.58869 | K18: =Schedules!J172*-1 -> -928.74147 | M18: =_xlfn.RRI($K$9-$F$9,F18,K18) -> 0.21715762 | N18: =_xlfn.RRI($K$9-$H$9,H18,K18) -> 0.095285916
B19: Executive Compensation | D19: =INDEX(' Income Statement'!$E$8:$G$27,MATCH('3 Statement Model'!$B19,' Income Statement'!$B$8:$B$27,0),MATCH('3 Statement Model'!D$9,' Income Statement'!$E$6:$G$6,0)) -> -2602.8996 | E19: =INDEX(' Income Statement'!$E$8:$G$27,MATCH('3 Statement Model'!$B19,' Income Statement'!$B$8:$B$27,0),MATCH('3 Statement Model'!E$9,' Income Statement'!$E$6:$G$6,0)) -> -2733.2592 | F19: =INDEX(' Income Statement'!$E$8:$G$27,MATCH('3 Statement Model'!$B19,' Income Statement'!$B$8:$B$27,0),MATCH('3 Statement Model'!F$9,' Income Statement'!$E$6:$G$6,0)) -> -2902.7796 | G19: =Schedules!F183*-1 -> -3420.2065 | H19: =Schedules!G183*-1 -> -3649.8651 | I19: =Schedules!H183*-1 -> -3897.735 | J19: =Schedules!I183*-1 -> -4142.9413 | K19: =Schedules!J183*-1 -> -4409.2232 | M19: =_xlfn.RRI($K$9-$F$9,F19,K19) -> 0.087200401 | N19: =_xlfn.RRI($K$9-$H$9,H19,K19) -> 0.065029794
B20: Marketing Costs | D20: =INDEX(' Income Statement'!$E$8:$G$27,MATCH('3 Statement Model'!$B20,' Income Statement'!$B$8:$B$27,0),MATCH('3 Statement Model'!D$9,' Income Statement'!$E$6:$G$6,0)) -> -1183.1344 | E20: =INDEX(' Income Statement'!$E$8:$G$27,MATCH('3 Statement Model'!$B20,' Income Statement'!$B$8:$B$27,0),MATCH('3 Statement Model'!E$9,' Income Statement'!$E$6:$G$6,0)) -> -1314.0624 | F20: =INDEX(' Income Statement'!$E$8:$G$27,MATCH('3 Statement Model'!$B20,' Income Statement'!$B$8:$B$27,0),MATCH('3 Statement Model'!F$9,' Income Statement'!$E$6:$G$6,0)) -> -1451.38 | G20: =Schedules!F177*-1 -> -1600.6721 | H20: =Schedules!G177*-1 -> -1767.0642 | I20: =Schedules!H177*-1 -> -1948.1327 | J20: =Schedules!I177*-1 -> -2126.4717 | K20: =Schedules!J177*-1 -> -2321.8537 | M20: =_xlfn.RRI($K$9-$F$9,F20,K20) -> 0.098527017 | N20: =_xlfn.RRI($K$9-$H$9,H20,K20) -> 0.095285916
B21: Rent | D21: =INDEX(' Income Statement'!$E$8:$G$27,MATCH('3 Statement Model'!$B21,' Income Statement'!$B$8:$B$27,0),MATCH('3 Statement Model'!D$9,' Income Statement'!$E$6:$G$6,0)) -> -1216.9248 | E21: =INDEX(' Income Statement'!$E$8:$G$27,MATCH('3 Statement Model'!$B21,' Income Statement'!$B$8:$B$27,0),MATCH('3 Statement Model'!E$9,' Income Statement'!$E$6:$G$6,0)) -> -1261.4952 | F21: =INDEX(' Income Statement'!$E$8:$G$27,MATCH('3 Statement Model'!$B21,' Income Statement'!$B$8:$B$27,0),MATCH('3 Statement Model'!F$9,' Income Statement'!$E$6:$G$6,0)) -> -1274 | G21: =Schedules!F158*-1 -> -1274 | H21: =Schedules!G158*-1 -> -1574 | I21: =Schedules!H158*-1 -> -1574 | J21: =Schedules!I158*-1 -> -1574 | K21: =Schedules!J158*-1 -> -1574 | M21: =_xlfn.RRI($K$9-$F$9,F21,K21) -> 0.043198755 | N21: =_xlfn.RRI($K$9-$H$9,H21,K21) -> 0
B22: Retailer Commission | D22: =INDEX(' Income Statement'!$E$8:$G$27,MATCH('3 Statement Model'!$B22,' Income Statement'!$B$8:$B$27,0),MATCH('3 Statement Model'!D$9,' Income Statement'!$E$6:$G$6,0)) -> -7098.8378 | E22: =INDEX(' Income Statement'!$E$8:$G$27,MATCH('3 Statement Model'!$B22,' Income Statement'!$B$8:$B$27,0),MATCH('3 Statement Model'!E$9,' Income Statement'!$E$6:$G$6,0)) -> -7884.4332 | F22: =INDEX(' Income Statement'!$E$8:$G$27,MATCH('3 Statement Model'!$B22,' Income Statement'!$B$8:$B$27,0),MATCH('3 Statement Model'!F$9,' Income Statement'!$E$6:$G$6,0)) -> -8708.3388 | G22: =Schedules!F167*-1 -> -9604.0328 | H22: =Schedules!G167*-1 -> -10602.385 | I22: =Schedules!H167*-1 -> -11688.796 | J22: =Schedules!I167*-1 -> -13609.419 | K22: =Schedules!J167*-1 -> -14859.863 | M22: =_xlfn.RRI($K$9-$F$9,F22,K22) -> 0.11279688 | N22: =_xlfn.RRI($K$9-$H$9,H22,K22) -> 0.1191039
B23: Salaries and Wages | D23: =INDEX(' Income Statement'!$E$8:$G$27,MATCH('3 Statement Model'!$B23,' Income Statement'!$B$8:$B$27,0),MATCH('3 Statement Model'!D$9,' Income Statement'!$E$6:$G$6,0)) -> -4862.27 | E23: =INDEX(' Income Statement'!$E$8:$G$27,MATCH('3 Statement Model'!$B23,' Income Statement'!$B$8:$B$27,0),MATCH('3 Statement Model'!E$9,' Income Statement'!$E$6:$G$6,0)) -> -5151.1544 | F23: =INDEX(' Income Statement'!$E$8:$G$27,MATCH('3 Statement Model'!$B23,' Income Statement'!$B$8:$B$27,0),MATCH('3 Statement Model'!F$9,' Income Statement'!$E$6:$G$6,0)) -> -5711.2832 | G23: =Schedules!F162*-1 -> -5762.4196 | H23: =Schedules!G162*-1 -> -6361.4312 | I23: =Schedules!H162*-1 -> -7013.2777 | J23: =Schedules!I162*-1 -> -7655.2982 | K23: =Schedules!J162*-1 -> -8358.6732 | M23: =_xlfn.RRI($K$9-$F$9,F23,K23) -> 0.079147304 | N23: =_xlfn.RRI($K$9-$H$9,H23,K23) -> 0.095285916
B24: EBITDA | D24: =SUM(D15,D18:D23) -> 5845.5314 | E24: =SUM(E15,E18:E23) -> 7346.864 | F24: =SUM(F15,F18:F23) -> 9529.7748 | G24: =SUM(G15,G18:G23) -> 11560.387 | H24: =SUM(H15,H18:H23) -> 13652.155 | I24: =SUM(I15,I18:I23) -> 16383.425 | J24: =SUM(J15,J18:J23) -> 18409.171 | K24: =SUM(K15,K18:K23) -> 21552.247 | M24: =_xlfn.RRI($K$9-$F$9,F24,K24) -> 0.17728601 | N24: =_xlfn.RRI($K$9-$H$9,H24,K24) -> 0.16438636
B26: Less: Depreciation & Amortization
B27: Depreciation | D27: =INDEX(' Income Statement'!$E$8:$G$27,MATCH('3 Statement Model'!$B27,' Income Statement'!$B$8:$B$27,0),MATCH('3 Statement Model'!D$9,' Income Statement'!$E$6:$G$6,0)) -> -716.086 | E27: =INDEX(' Income Statement'!$E$8:$G$27,MATCH('3 Statement Model'!$B27,' Income Statement'!$B$8:$B$27,0),MATCH('3 Statement Model'!E$9,' Income Statement'!$E$6:$G$6,0)) -> -735.8624 | F27: =INDEX(' Income Statement'!$E$8:$G$27,MATCH('3 Statement Model'!$B27,' Income Statement'!$B$8:$B$27,0),MATCH('3 Statement Model'!F$9,' Income Statement'!$E$6:$G$6,0)) -> -783.3728 | G27: =Schedules!F224*-1 -> -1103.5072 | H27: =Schedules!G224*-1 -> -1456.9201 | I27: =Schedules!H224*-1 -> -1846.5466 | J27: =Schedules!I224*-1 -> -2271.841 | K27: =Schedules!J224*-1 -> -2736.2117 | M27: =_xlfn.RRI($K$9-$F$9,F27,K27) -> 0.28421057 | N27: =_xlfn.RRI($K$9-$H$9,H27,K27) -> 0.23378075
B28: Amortization | D28: =INDEX(' Income Statement'!$E$8:$G$27,MATCH('3 Statement Model'!$B28,' Income Statement'!$B$8:$B$27,0),MATCH('3 Statement Model'!D$9,' Income Statement'!$E$6:$G$6,0)) -> -294.4116 | E28: =INDEX(' Income Statement'!$E$8:$G$27,MATCH('3 Statement Model'!$B28,' Income Statement'!$B$8:$B$27,0),MATCH('3 Statement Model'!E$9,' Income Statement'!$E$6:$G$6,0)) -> -268.9512 | F28: =INDEX(' Income Statement'!$E$8:$G$27,MATCH('3 Statement Model'!$B28,' Income Statement'!$B$8:$B$27,0),MATCH('3 Statement Model'!F$9,' Income Statement'!$E$6:$G$6,0)) -> -232.2208 | G28: =Schedules!F235*-1 -> -360.27457 | H28: =Schedules!G235*-1 -> -501.63971 | I28: =Schedules!H235*-1 -> -657.49033 | J28: =Schedules!I235*-1 -> -827.60806 | K28: =Schedules!J235*-1 -> -1013.3564 | M28: =_xlfn.RRI($K$9-$F$9,F28,K28) -> 0.34267906 | N28: =_xlfn.RRI($K$9-$H$9,H28,K28) -> 0.26412522
B29: EBIT | D29: =SUM(D24,D27:D28) -> 4835.0338 | E29: =SUM(E24,E27:E28) -> 6342.0504 | F29: =SUM(F24,F27:F28) -> 8514.1812 | G29: =SUM(G24,G27:G28) -> 10096.605 | H29: =SUM(H24,H27:H28) -> 11693.596 | I29: =SUM(I24,I27:I28) -> 13879.388 | J29: =SUM(J24,J27:J28) -> 15309.722 | K29: =SUM(K24,K27:K28) -> 17802.679 | M29: =_xlfn.RRI($K$9-$F$9,F29,K29) -> 0.15896012 | N29: =_xlfn.RRI($K$9-$H$9,H29,K29) -> 0.15039176
B31: Less: Total Interest Expenses
B32: Loan Interest Expenses | D32: =INDEX(' Income Statement'!$E$8:$G$27,MATCH('3 Statement Model'!$B32,' Income Statement'!$B$8:$B$27,0),MATCH('3 Statement Model'!D$9,' Income Statement'!$E$6:$G$6,0)) -> -336.924 | E32: =INDEX(' Income Statement'!$E$8:$G$27,MATCH('3 Statement Model'!$B32,' Income Statement'!$B$8:$B$27,0),MATCH('3 Statement Model'!E$9,' Income Statement'!$E$6:$G$6,0)) -> -307.818 | F32: =INDEX(' Income Statement'!$E$8:$G$27,MATCH('3 Statement Model'!$B32,' Income Statement'!$B$8:$B$27,0),MATCH('3 Statement Model'!F$9,' Income Statement'!$E$6:$G$6,0)) -> -278.712 | G32: =-Schedules!F352 -> -653.1672 | H32: =-Schedules!G352 -> -707.0544 | I32: =-Schedules!H352 -> -733.3716 | J32: =-Schedules!I352 -> -733.1688 | K32: =-Schedules!J352 -> -732.446 | M32: =_xlfn.RRI($K$9-$F$9,F32,K32) -> 0.2131765 | N32: =_xlfn.RRI($K$9-$H$9,H32,K32) -> 0.011830099
B33: Rovolver Interest | D33: 0 | E33: 0 | F33: 0 | G33: =Schedules!F353 -> 0 | H33: 0 | I33: 0 | J33: 0 | K33: 0 | M33: =_xlfn.RRI($K$9-$F$9,F33,K33) -> 0 | N33: =_xlfn.RRI($K$9-$H$9,H33,K33) -> 0
B34: EBT | D34: =SUM(D29,D32:D33) -> 4498.1098 | E34: =SUM(E29,E32:E33) -> 6034.2324 | F34: =SUM(F29,F32:F33) -> 8235.4692 | G34: =SUM(G29,G32:G33) -> 9443.4378 | H34: =SUM(H29,H32:H33) -> 10986.541 | I34: =SUM(I29,I32:I33) -> 13146.016 | J34: =SUM(J29,J32:J33) -> 14576.553 | K34: =SUM(K29,K32:K33) -> 17070.233 | M34: =_xlfn.RRI($K$9-$F$9,F34,K34) -> 0.15693836 | N34: =_xlfn.RRI($K$9-$H$9,H34,K34) -> 0.15822469
B36: Less: Taxes | D36: =INDEX(' Income Statement'!$E$8:$G$27,MATCH('3 Statement Model'!$B36,' Income Statement'!$B$8:$B$27,0),MATCH('3 Statement Model'!D$9,' Income Statement'!$E$6:$G$6,0)) -> -906.36913 | E36: =INDEX(' Income Statement'!$E$8:$G$27,MATCH('3 Statement Model'!$B36,' Income Statement'!$B$8:$B$27,0),MATCH('3 Statement Model'!E$9,' Income Statement'!$E$6:$G$6,0)) -> -1215.8978 | F36: =INDEX(' Income Statement'!$E$8:$G$27,MATCH('3 Statement Model'!$B36,' Income Statement'!$B$8:$B$27,0),MATCH('3 Statement Model'!F$9,' Income Statement'!$E$6:$G$6,0)) -> -1659.447 | G36: =Schedules!F256 -> -2360.8595 | H36: =Schedules!G256 -> -2746.6353 | I36: =Schedules!H256 -> -3286.504 | J36: =Schedules!I256 -> -3644.1383 | K36: =Schedules!J256 -> -4267.5582 | M36: =_xlfn.RRI($K$9-$F$9,F36,K36) -> 0.20793401 | N36: =_xlfn.RRI($K$9-$H$9,H36,K36) -> 0.15822469
B37: Net Income | D37: =SUM(D34,D36) -> 3591.7407 | E37: =SUM(E34,E36) -> 4818.3346 | F37: =SUM(F34,F36) -> 6576.0222 | G37: =SUM(G34,G36) -> 7082.5784 | H37: =SUM(H34,H36) -> 8239.9059 | I37: =SUM(I34,I36) -> 9859.512 | J37: =SUM(J34,J36) -> 10932.415 | K37: =SUM(K34,K36) -> 12802.675 | M37: =_xlfn.RRI($K$9-$F$9,F37,K37) -> 0.14252967 | N37: =_xlfn.RRI($K$9-$H$9,H37,K37) -> 0.15822469
B39: Sales Growth % | D39: =IFERROR(D13/C13-1,"NM") -> NM | E39: =IFERROR(E13/D13-1,"NM") -> 0.11066774 | F39: =IFERROR(F13/E13-1,"NM") -> 0.10449607 | G39: =IFERROR(G13/F13-1,"NM") -> 0.10285437 | H39: =IFERROR(H13/G13-1,"NM") -> 0.1039514 | I39: =IFERROR(I13/H13-1,"NM") -> 0.10246853 | J39: =IFERROR(J13/I13-1,"NM") -> 0.091543562 | K39: =IFERROR(K13/J13-1,"NM") -> 0.091880815
B40: Gross Profit Margin % | D40: =IFERROR(D15/D13,"NM") -> 0.48799993 | E40: =IFERROR(E15/E13,"NM") -> 0.49475965 | F40: =IFERROR(F15/F13,"NM") -> 0.51545786 | G40: =IFERROR(G15/G13,"NM") -> 0.52887138 | H40: =IFERROR(H15/H13,"NM") -> 0.5420534 | I40: =IFERROR(I15/I13,"NM") -> 0.55546292 | J40: =IFERROR(J15/J13,"NM") -> 0.56864018 | K40: =IFERROR(K15/K13,"NM") -> 0.58148154
B41: EBITDA Margin % | D41: =IFERROR(D24/D13,"NM") -> 0.1235174 | E41: =IFERROR(E24/E13,"NM") -> 0.13977258 | F41: =IFERROR(F24/F13,"NM") -> 0.16414907 | G41: =IFERROR(G24/G13,"NM") -> 0.1805552 | H41: =IFERROR(H24/H13,"NM") -> 0.19314741 | I41: =IFERROR(I24/I13,"NM") -> 0.21024523 | J41: =IFERROR(J24/J13,"NM") -> 0.21642859 | K41: =IFERROR(K24/K13,"NM") -> 0.23205863
B42: EBIT Margin % | D42: =IFERROR(D29/D13,"NM") -> 0.10216535 | E42: =IFERROR(E29/E13,"NM") -> 0.1206562 | F42: =IFERROR(F29/F13,"NM") -> 0.14665561 | G42: =IFERROR(G29/G13,"NM") -> 0.15769321 | H42: =IFERROR(H29/H13,"NM") -> 0.16543818 | I42: =IFERROR(I29/I13,"NM") -> 0.17811142 | J42: =IFERROR(J29/J13,"NM") -> 0.17998972 | K42: =IFERROR(K29/K13,"NM") -> 0.19168606
B43: Actual Tax Rate % | D43: =-IFERROR(D36/D34,"NM") -> 0.2015 | E43: =-IFERROR(E36/E34,"NM") -> 0.2015 | F43: =-IFERROR(F36/F34,"NM") -> 0.2015 | G43: =-IFERROR(G36/G34,"NM") -> 0.25 | H43: =-IFERROR(H36/H34,"NM") -> 0.25 | I43: =-IFERROR(I36/I34,"NM") -> 0.25 | J43: =-IFERROR(J36/J34,"NM") -> 0.25 | K43: =-IFERROR(K36/K34,"NM") -> 0.25
B44: Net Income Margin % | D44: =IFERROR(D37/D13,"NM") -> 0.07589429 | E44: =IFERROR(E37/E13,"NM") -> 0.091667824 | F44: =IFERROR(F37/F13,"NM") -> 0.11327109 | G44: =IFERROR(G37/G13,"NM") -> 0.11061882 | H44: =IFERROR(H37/H13,"NM") -> 0.11657621 | I44: =IFERROR(I37/I13,"NM") -> 0.12652516 | J44: =IFERROR(J37/J13,"NM") -> 0.12852763 | K44: =IFERROR(K37/K13,"NM") -> 0.13784971
A46: # | B46: Balance Sheet
B48: Assets
B49: Cash | D49: =INDEX(' Balance Sheet'!$E$9:$G$40,MATCH('3 Statement Model'!$B49,' Balance Sheet'!$B$9:$B$40,0),MATCH('3 Statement Model'!D$9,' Balance Sheet'!$E$6:$G$6,0)) -> 1471.2348 | E49: =INDEX(' Balance Sheet'!$E$9:$G$40,MATCH('3 Statement Model'!$B49,' Balance Sheet'!$B$9:$B$40,0),MATCH('3 Statement Model'!E$9,' Balance Sheet'!$E$6:$G$6,0)) -> 1956.0604 | F49: =INDEX(' Balance Sheet'!$E$9:$G$40,MATCH('3 Statement Model'!$B49,' Balance Sheet'!$B$9:$B$40,0),MATCH('3 Statement Model'!F$9,' Balance Sheet'!$E$6:$G$6,0)) -> 2181.2644 | G49: =G116 -> 3386.2058 | H49: =H116 -> 5257.902 | I49: =I116 -> 7677.0036 | J49: =J116 -> 10878.163 | K49: =K116 -> 15353.393
B50: Inventory | D50: =INDEX(' Balance Sheet'!$E$9:$G$40,MATCH('3 Statement Model'!$B50,' Balance Sheet'!$B$9:$B$40,0),MATCH('3 Statement Model'!D$9,' Balance Sheet'!$E$6:$G$6,0)) -> 4686.8108 | E50: =INDEX(' Balance Sheet'!$E$9:$G$40,MATCH('3 Statement Model'!$B50,' Balance Sheet'!$B$9:$B$40,0),MATCH('3 Statement Model'!E$9,' Balance Sheet'!$E$6:$G$6,0)) -> 5155.486 | F50: =INDEX(' Balance Sheet'!$E$9:$G$40,MATCH('3 Statement Model'!$B50,' Balance Sheet'!$B$9:$B$40,0),MATCH('3 Statement Model'!F$9,' Balance Sheet'!$E$6:$G$6,0)) -> 5592.6248 | G50: =Schedules!F280 -> 6000.7099 | H50: =Schedules!G280 -> 6439.141 | I50: =Schedules!H280 -> 6891.08 | J50: =Schedules!I280 -> 7298.9445 | K50: =Schedules!J280 -> 7732.3272
B51: Debtors | D51: =INDEX(' Balance Sheet'!$E$9:$G$40,MATCH('3 Statement Model'!$B51,' Balance Sheet'!$B$9:$B$40,0),MATCH('3 Statement Model'!D$9,' Balance Sheet'!$E$6:$G$6,0)) -> 5476.2792 | E51: =INDEX(' Balance Sheet'!$E$9:$G$40,MATCH('3 Statement Model'!$B51,' Balance Sheet'!$B$9:$B$40,0),MATCH('3 Statement Model'!E$9,' Balance Sheet'!$E$6:$G$6,0)) -> 6023.9032 | F51: =INDEX(' Balance Sheet'!$E$9:$G$40,MATCH('3 Statement Model'!$B51,' Balance Sheet'!$B$9:$B$40,0),MATCH('3 Statement Model'!F$9,' Balance Sheet'!$E$6:$G$6,0)) -> 6550.7708 | G51: =Schedules!F275 -> 7230.2267 | H51: =Schedules!G275 -> 7981.8188 | I51: =Schedules!H275 -> 8799.7041 | J51: =Schedules!I275 -> 9605.2603 | K51: =Schedules!J275 -> 10487.799
B52: Prepaid Expenses | D52: =INDEX(' Balance Sheet'!$E$9:$G$40,MATCH('3 Statement Model'!$B52,' Balance Sheet'!$B$9:$B$40,0),MATCH('3 Statement Model'!D$9,' Balance Sheet'!$E$6:$G$6,0)) -> 1660.1396 | E52: =INDEX(' Balance Sheet'!$E$9:$G$40,MATCH('3 Statement Model'!$B52,' Balance Sheet'!$B$9:$B$40,0),MATCH('3 Statement Model'!E$9,' Balance Sheet'!$E$6:$G$6,0)) -> 1915.0964 | F52: =INDEX(' Balance Sheet'!$E$9:$G$40,MATCH('3 Statement Model'!$B52,' Balance Sheet'!$B$9:$B$40,0),MATCH('3 Statement Model'!F$9,' Balance Sheet'!$E$6:$G$6,0)) -> 2186.9876 | G52: =Schedules!F285 -> 2413.8253 | H52: =Schedules!G285 -> 2664.7458 | I52: =Schedules!H285 -> 2937.7984 | J52: =Schedules!I285 -> 3206.7349 | K52: =Schedules!J285 -> 3501.3723
B53: Other Current Assets | D53: =INDEX(' Balance Sheet'!$E$9:$G$40,MATCH('3 Statement Model'!$B53,' Balance Sheet'!$B$9:$B$40,0),MATCH('3 Statement Model'!D$9,' Balance Sheet'!$E$6:$G$6,0)) -> 97.608 | E53: =INDEX(' Balance Sheet'!$E$9:$G$40,MATCH('3 Statement Model'!$B53,' Balance Sheet'!$B$9:$B$40,0),MATCH('3 Statement Model'!E$9,' Balance Sheet'!$E$6:$G$6,0)) -> 130.0068 | F53: =INDEX(' Balance Sheet'!$E$9:$G$40,MATCH('3 Statement Model'!$B53,' Balance Sheet'!$B$9:$B$40,0),MATCH('3 Statement Model'!F$9,' Balance Sheet'!$E$6:$G$6,0)) -> 151.1552 | G53: =Schedules!F290 -> 166.83325 | H53: =Schedules!G290 -> 184.1758 | I53: =Schedules!H290 -> 203.04802 | J53: =Schedules!I290 -> 221.63576 | K53: =Schedules!J290 -> 241.99983
B54: Total Current Assets | D54: =SUM(D49:D53) -> 13392.072 | E54: =SUM(E49:E53) -> 15180.553 | F54: =SUM(F49:F53) -> 16662.803 | G54: =SUM(G49:G53) -> 19197.801 | H54: =SUM(H49:H53) -> 22527.783 | I54: =SUM(I49:I53) -> 26508.634 | J54: =SUM(J49:J53) -> 31210.739 | K54: =SUM(K49:K53) -> 37316.891
B56: Net Property, Plant & Equipment | D56: =INDEX(' Balance Sheet'!$E$9:$G$40,MATCH('3 Statement Model'!$B56,' Balance Sheet'!$B$9:$B$40,0),MATCH('3 Statement Model'!D$9,' Balance Sheet'!$E$6:$G$6,0)) -> 7007 | E56: =INDEX(' Balance Sheet'!$E$9:$G$40,MATCH('3 Statement Model'!$B56,' Balance Sheet'!$B$9:$B$40,0),MATCH('3 Statement Model'!E$9,' Balance Sheet'!$E$6:$G$6,0)) -> 8309.322 | F56: =INDEX(' Balance Sheet'!$E$9:$G$40,MATCH('3 Statement Model'!$B56,' Balance Sheet'!$B$9:$B$40,0),MATCH('3 Statement Model'!F$9,' Balance Sheet'!$E$6:$G$6,0)) -> 9491.3 | G56: =Schedules!F208 -> 11589.137 | H56: =Schedules!G208 -> 13666.345 | I56: =Schedules!H208 -> 15716.064 | J56: =Schedules!I208 -> 17697.167 | K56: =Schedules!J208 -> 19604.662
B57: Net Intangible Assets | D57: =INDEX(' Balance Sheet'!$E$9:$G$40,MATCH('3 Statement Model'!$B57,' Balance Sheet'!$B$9:$B$40,0),MATCH('3 Statement Model'!D$9,' Balance Sheet'!$E$6:$G$6,0)) -> 2500.078 | E57: =INDEX(' Balance Sheet'!$E$9:$G$40,MATCH('3 Statement Model'!$B57,' Balance Sheet'!$B$9:$B$40,0),MATCH('3 Statement Model'!E$9,' Balance Sheet'!$E$6:$G$6,0)) -> 2598.1015 | F57: =INDEX(' Balance Sheet'!$E$9:$G$40,MATCH('3 Statement Model'!$B57,' Balance Sheet'!$B$9:$B$40,0),MATCH('3 Statement Model'!F$9,' Balance Sheet'!$E$6:$G$6,0)) -> 2854.5636 | G57: =Schedules!F213 -> 4415.0956 | H57: =Schedules!G213 -> 6033.9329 | I57: =Schedules!H213 -> 7714.2019 | J57: =Schedules!I213 -> 9438.3599 | K57: =Schedules!J213 -> 11211.228
B58: Goodwill | D58: =INDEX(' Balance Sheet'!$E$9:$G$40,MATCH('3 Statement Model'!$B58,' Balance Sheet'!$B$9:$B$40,0),MATCH('3 Statement Model'!D$9,' Balance Sheet'!$E$6:$G$6,0)) -> 0 | E58: =INDEX(' Balance Sheet'!$E$9:$G$40,MATCH('3 Statement Model'!$B58,' Balance Sheet'!$B$9:$B$40,0),MATCH('3 Statement Model'!E$9,' Balance Sheet'!$E$6:$G$6,0)) -> 0 | F58: 0 | G58: 0 | H58: 0 | I58: 0 | J58: 0 | K58: 0
B59: Other Non-Current Assets | D59: =INDEX(' Balance Sheet'!$E$9:$G$40,MATCH('3 Statement Model'!$B59,' Balance Sheet'!$B$9:$B$40,0),MATCH('3 Statement Model'!D$9,' Balance Sheet'!$E$6:$G$6,0)) -> 1130.43 | E59: =INDEX(' Balance Sheet'!$E$9:$G$40,MATCH('3 Statement Model'!$B59,' Balance Sheet'!$B$9:$B$40,0),MATCH('3 Statement Model'!E$9,' Balance Sheet'!$E$6:$G$6,0)) -> 1700.5352 | F59: 1825.5636 | G59: 1825.5636 | H59: 1825.5636 | I59: 1825.5636 | J59: 1825.5636 | K59: 1825.5636
B60: Total Non-Current Assets | D60: =SUM(D56:D59) -> 10637.508 | E60: =SUM(E56:E59) -> 12607.959 | F60: =SUM(F56:F59) -> 14171.427 | G60: =SUM(G56:G59) -> 17829.796 | H60: =SUM(H56:H59) -> 21525.842 | I60: =SUM(I56:I59) -> 25255.83 | J60: =SUM(J56:J59) -> 28961.09 | K60: =SUM(K56:K59) -> 32641.454
B62: Total Assets | D62: =SUM(D60,D54) -> 24029.58 | E62: =SUM(E60,E54) -> 27788.512 | F62: =SUM(F60,F54) -> 30834.23 | G62: =SUM(G60,G54) -> 37027.597 | H62: =SUM(H60,H54) -> 44053.625 | I62: =SUM(I60,I54) -> 51764.464 | J62: =SUM(J60,J54) -> 60171.829 | K62: =SUM(K60,K54) -> 69958.345
B65: Liabilities and Shareholders' Equity
B66: Creditors | D66: =INDEX(' Balance Sheet'!$E$9:$G$40,MATCH('3 Statement Model'!$B66,' Balance Sheet'!$B$9:$B$40,0),MATCH('3 Statement Model'!D$9,' Balance Sheet'!$E$6:$G$6,0)) -> 4691.1032 | E66: =INDEX(' Balance Sheet'!$E$9:$G$40,MATCH('3 Statement Model'!$B66,' Balance Sheet'!$B$9:$B$40,0),MATCH('3 Statement Model'!E$9,' Balance Sheet'!$E$6:$G$6,0)) -> 5396.8404 | F66: =INDEX(' Balance Sheet'!$E$9:$G$40,MATCH('3 Statement Model'!$B66,' Balance Sheet'!$B$9:$B$40,0),MATCH('3 Statement Model'!F$9,' Balance Sheet'!$E$6:$G$6,0)) -> 6055.812 | G66: =Schedules!F295 -> 6497.6952 | H66: =Schedules!G295 -> 6972.4375 | I66: =Schedules!H295 -> 7461.8066 | J66: =Schedules!I295 -> 7903.4509 | K66: =Schedules!J295 -> 8372.7268
B67: Other Payables | D67: =INDEX(' Balance Sheet'!$E$9:$G$40,MATCH('3 Statement Model'!$B67,' Balance Sheet'!$B$9:$B$40,0),MATCH('3 Statement Model'!D$9,' Balance Sheet'!$E$6:$G$6,0)) -> 2628.164 | E67: =INDEX(' Balance Sheet'!$E$9:$G$40,MATCH('3 Statement Model'!$B67,' Balance Sheet'!$B$9:$B$40,0),MATCH('3 Statement Model'!E$9,' Balance Sheet'!$E$6:$G$6,0)) -> 3061.0104 | F67: =INDEX(' Balance Sheet'!$E$9:$G$40,MATCH('3 Statement Model'!$B67,' Balance Sheet'!$B$9:$B$40,0),MATCH('3 Statement Model'!F$9,' Balance Sheet'!$E$6:$G$6,0)) -> 3343.4072 | G67: =Schedules!F300 -> 3690.1905 | H67: =Schedules!G300 -> 4073.7909 | I67: =Schedules!H300 -> 4491.2263 | J67: =Schedules!I300 -> 4902.3691 | K67: =Schedules!J300 -> 5352.8028
B68: Other Current Liabilities | D68: =INDEX(' Balance Sheet'!$E$9:$G$40,MATCH('3 Statement Model'!$B68,' Balance Sheet'!$B$9:$B$40,0),MATCH('3 Statement Model'!D$9,' Balance Sheet'!$E$6:$G$6,0)) -> 187.6308 | E68: =INDEX(' Balance Sheet'!$E$9:$G$40,MATCH('3 Statement Model'!$B68,' Balance Sheet'!$B$9:$B$40,0),MATCH('3 Statement Model'!E$9,' Balance Sheet'!$E$6:$G$6,0)) -> 215.8548 | F68: =INDEX(' Balance Sheet'!$E$9:$G$40,MATCH('3 Statement Model'!$B68,' Balance Sheet'!$B$9:$B$40,0),MATCH('3 Statement Model'!F$9,' Balance Sheet'!$E$6:$G$6,0)) -> 259.308 | G68: =Schedules!F305 -> 286.20382 | H68: =Schedules!G305 -> 315.95511 | I68: =Schedules!H305 -> 348.33056 | J68: =Schedules!I305 -> 380.21798 | K68: =Schedules!J305 -> 415.15272
B69: Total Current Liabilities | D69: =SUM(D66:D68) -> 7506.898 | E69: =SUM(E66:E68) -> 8673.7056 | F69: =SUM(F66:F68) -> 9658.5272 | G69: =SUM(G66:G68) -> 10474.089 | H69: =SUM(H66:H68) -> 11362.184 | I69: =SUM(I66:I68) -> 12301.363 | J69: =SUM(J66:J68) -> 13186.038 | K69: =SUM(K66:K68) -> 14140.682
B71: Senior Term Loan | D71: =INDEX(' Balance Sheet'!$E$9:$G$40,MATCH('3 Statement Model'!$B71,' Balance Sheet'!$B$9:$B$40,0),MATCH('3 Statement Model'!D$9,' Balance Sheet'!$E$6:$G$6,0)) -> 7487.2 | E71: =INDEX(' Balance Sheet'!$E$9:$G$40,MATCH('3 Statement Model'!$B71,' Balance Sheet'!$B$9:$B$40,0),MATCH('3 Statement Model'!E$9,' Balance Sheet'!$E$6:$G$6,0)) -> 6840.4 | F71: =INDEX(' Balance Sheet'!$E$9:$G$40,MATCH('3 Statement Model'!$B71,' Balance Sheet'!$B$9:$B$40,0),MATCH('3 Statement Model'!F$9,' Balance Sheet'!$E$6:$G$6,0)) -> 6193.6 | G71: =Schedules!F328 -> 6613.6 | H71: =Schedules!G328 -> 6983.6 | I71: =Schedules!H328 -> 6853.6 | J71: =Schedules!I328 -> 6723.6 | K71: =Schedules!J328 -> 6593.6
B72: Revolving Credit | D72: =INDEX(' Balance Sheet'!$E$9:$G$40,MATCH('3 Statement Model'!$B72,' Balance Sheet'!$B$9:$B$40,0),MATCH('3 Statement Model'!D$9,' Balance Sheet'!$E$6:$G$6,0)) -> 0 | E72: =INDEX(' Balance Sheet'!$E$9:$G$40,MATCH('3 Statement Model'!$B72,' Balance Sheet'!$B$9:$B$40,0),MATCH('3 Statement Model'!E$9,' Balance Sheet'!$E$6:$G$6,0)) -> 0 | F72: 0 | G72: =Schedules!F242 -> 0 | H72: =Schedules!G242 -> 0 | I72: =Schedules!H242 -> 0 | J72: =Schedules!I242 -> 0 | K72: =Schedules!J242 -> 0
B73: Other Non-Current Liabilities | D73: =INDEX(' Balance Sheet'!$E$9:$G$40,MATCH('3 Statement Model'!$B73,' Balance Sheet'!$B$9:$B$40,0),MATCH('3 Statement Model'!D$9,' Balance Sheet'!$E$6:$G$6,0)) -> 449.428 | E73: =INDEX(' Balance Sheet'!$E$9:$G$40,MATCH('3 Statement Model'!$B73,' Balance Sheet'!$B$9:$B$40,0),MATCH('3 Statement Model'!E$9,' Balance Sheet'!$E$6:$G$6,0)) -> 1807.0808 | F73: 903.5404 | G73: 903.5404 | H73: 903.5404 | I73: 903.5404 | J73: 903.5404 | K73: 903.5404
B74: Total Non-Current Liabilities | D74: =SUM(D71:D73) -> 7936.628 | E74: =SUM(E71:E73) -> 8647.4808 | F74: =SUM(F71:F73) -> 7097.1404 | G74: =SUM(G71:G73) -> 7517.1404 | H74: =SUM(H71:H73) -> 7887.1404 | I74: =SUM(I71:I73) -> 7757.1404 | J74: =SUM(J71:J73) -> 7627.1404 | K74: =SUM(K71:K73) -> 7497.1404
B76: Equity Shares | D76: =INDEX(' Balance Sheet'!$E$9:$G$40,MATCH('3 Statement Model'!$B76,' Balance Sheet'!$B$9:$B$40,0),MATCH('3 Statement Model'!D$9,' Balance Sheet'!$E$6:$G$6,0)) -> 980 | E76: =INDEX(' Balance Sheet'!$E$9:$G$40,MATCH('3 Statement Model'!$B76,' Balance Sheet'!$B$9:$B$40,0),MATCH('3 Statement Model'!E$9,' Balance Sheet'!$E$6:$G$6,0)) -> 980 | F76: =INDEX(' Balance Sheet'!$E$9:$G$40,MATCH('3 Statement Model'!$B76,' Balance Sheet'!$B$9:$B$40,0),MATCH('3 Statement Model'!F$9,' Balance Sheet'!$E$6:$G$6,0)) -> 980 | G76: =F76 -> 980 | H76: =G76 -> 980 | I76: =H76 -> 980 | J76: =I76 -> 980 | K76: =J76 -> 980
B77: Retained Earnings | D77: =INDEX(' Balance Sheet'!$E$9:$G$40,MATCH('3 Statement Model'!$B77,' Balance Sheet'!$B$9:$B$40,0),MATCH('3 Statement Model'!D$9,' Balance Sheet'!$E$6:$G$6,0)) -> 7606.0544 | E77: =INDEX(' Balance Sheet'!$E$9:$G$40,MATCH('3 Statement Model'!$B77,' Balance Sheet'!$B$9:$B$40,0),MATCH('3 Statement Model'!E$9,' Balance Sheet'!$E$6:$G$6,0)) -> 9487.3251 | F77: =INDEX(' Balance Sheet'!$E$9:$G$40,MATCH('3 Statement Model'!$B77,' Balance Sheet'!$B$9:$B$40,0),MATCH('3 Statement Model'!F$9,' Balance Sheet'!$E$6:$G$6,0)) -> 13098.562 | G77: =Schedules!F266 -> 18056.367 | H77: =Schedules!G266 -> 23824.301 | I77: =Schedules!H266 -> 30725.96 | J77: =Schedules!I266 -> 38378.65 | K77: =Schedules!J266 -> 47340.523
B78: Total Shareholders' Equity | D78: =SUM(D76:D77) -> 8586.0544 | E78: =SUM(E76:E77) -> 10467.325 | F78: =SUM(F76:F77) -> 14078.562 | G78: =SUM(G76:G77) -> 19036.367 | H78: =SUM(H76:H77) -> 24804.301 | I78: =SUM(I76:I77) -> 31705.96 | J78: =SUM(J76:J77) -> 39358.65 | K78: =SUM(K76:K77) -> 48320.523
B80: Total Liabilities and Shareholders' Equity | D80: =SUM(D78,D74,D69) -> 24029.58 | E80: =SUM(E78,E74,E69) -> 27788.512 | F80: =SUM(F78,F74,F69) -> 30834.23 | G80: =SUM(G78,G74,G69) -> 37027.597 | H80: =SUM(H78,H74,H69) -> 44053.625 | I80: =SUM(I78,I74,I69) -> 51764.464 | J80: =SUM(J78,J74,J69) -> 60171.829 | K80: =SUM(K78,K74,K69) -> 69958.345
B84: Net Working Capital | D84: =D54-D69 -> 5885.1744 | E84: =E54-E69 -> 6506.8472 | F84: =F54-F69 -> 7004.2756 | G84: =G54-G69 -> 8723.7115 | H84: =H54-H69 -> 11165.6 | I84: =I54-I69 -> 14207.271 | J84: =J54-J69 -> 18024.701 | K84: =K54-K69 -> 23176.209
B85: Debtors Days | D85: =D51/D13*365 -> 42.23598 | E85: =E51/E13*365 -> 41.830285 | F85: =F51/F13*365 -> 41.185189 | G85: =G51/G13*365 -> 41.217572 | H85: =H51/H13*365 -> 41.217572 | I85: =I51/I13*365 -> 41.217572 | J85: =J51/J13*365 -> 41.217572 | K85: =K51/K13*365 -> 41.217572
B86: Inventory Days | D86: =D50/D14*365*-1 -> 70.599951 | E86: =E50/E14*365*-1 -> 70.85727 | F86: =F50/F14*365*-1 -> 72.565934 | G86: =G50/G14*365*-1 -> 72.609531 | H86: =H50/H14*365*-1 -> 72.609531 | I86: =I50/I14*365*-1 -> 72.609531 | J86: =J50/J14*365*-1 -> 72.609531 | K86: =K50/K14*365*-1 -> 72.609531
B87: Creditor Days | D87: =D66/D14*365*-1 -> 70.664609 | E87: =E66/E14*365*-1 -> 74.174458 | F87: =F66/F14*365*-1 -> 78.575923 | G87: =G66/G14*365*-1 -> 78.623131 | H87: =H66/H14*365*-1 -> 78.623131 | I87: =I66/I14*365*-1 -> 78.623131 | J87: =J66/J14*365*-1 -> 78.623131 | K87: =K66/K14*365*-1 -> 78.623131
B88: Prepaid Expenses % Sales | D88: =D52/D13 -> 0.035079124 | E88: =E52/E13 -> 0.036434315 | F88: =F52/F13 -> 0.037670563 | G88: =G52/G13 -> 0.037700183 | H88: =H52/H13 -> 0.037700183 | I88: =I52/I13 -> 0.037700183 | J88: =J52/J13 -> 0.037700183 | K88: =K52/K13 -> 0.037700183
B89: Other Current Asset % Sales | D89: =D53/D13 -> 0.002062479 | E89: =E53/E13 -> 0.0024733526 | F89: =F53/F13 -> 0.0026036277 | G89: =G53/G13 -> 0.0026056749 | H89: =H53/H13 -> 0.0026056749 | I89: =I53/I13 -> 0.0026056749 | J89: =J53/J13 -> 0.0026056749 | K89: =K53/K13 -> 0.0026056749
B90: Other Current Liabilities % Sales | D90: =D68/D13 -> 0.0039646811 | E90: =E68/E13 -> 0.0041065932 | F90: =F68/F13 -> 0.004466545 | G90: =G68/G13 -> 0.0044700569 | H90: =H68/H13 -> 0.0044700569 | I90: =I68/I13 -> 0.0044700569 | J90: =J68/J13 -> 0.0044700569 | K90: =K68/K13 -> 0.0044700569
B91: Other Payable % Sales | D91: =D67/D13 -> 0.055533698 | E91: =E67/E13 -> 0.058235093 | F91: =F67/F13 -> 0.057589733 | G91: =G67/G13 -> 0.057635015 | H91: =H67/H13 -> 0.057635015 | I91: =I67/I13 -> 0.057635015 | J91: =J67/J13 -> 0.057635015 | K91: =K67/K13 -> 0.057635015
A93: # | B93: Cash Flow Statement
B95: Net Income | G95: =G37 -> 7082.5784 | H95: =H37 -> 8239.9059 | I95: =I37 -> 9859.512 | J95: =J37 -> 10932.415 | K95: =K37 -> 12802.675
B96: Add: Interest Expenses | G96: =-G32 -> 653.1672 | H96: =-H32 -> 707.0544 | I96: =-I32 -> 733.3716 | J96: =-J32 -> 733.1688 | K96: =-K32 -> 732.446
B97: Less: Revolver Expenses | G97: =G33 -> 0 | H97: =H33 -> 0 | I97: =I33 -> 0 | J97: =J33 -> 0 | K97: =K33 -> 0
B98: Add: Depreciation | G98: =G27*-1 -> 1103.5072 | H98: =H27*-1 -> 1456.9201 | I98: =I27*-1 -> 1846.5466 | J98: =J27*-1 -> 2271.841 | K98: =K27*-1 -> 2736.2117
B99: Add: Amortization | G99: =G28*-1 -> 360.27457 | H99: =H28*-1 -> 501.63971 | I99: =I28*-1 -> 657.49033 | J99: =J28*-1 -> 827.60806 | K99: =K28*-1 -> 1013.3564
B100: Less: Change in Working Capital | G100: =Schedules!F321*-1 -> -514.49445 | H100: =Schedules!G321*-1 -> -570.19216 | I100: =Schedules!H321*-1 -> -622.56916 | J100: =Schedules!I321*-1 -> -616.27047 | K100: =Schedules!J321*-1 -> -676.27901
B101: Cash Flow from Operation | G101: =SUM(G95:G100) -> 8685.0329 | H101: =SUM(H95:H100) -> 10335.328 | I101: =SUM(I95:I100) -> 12474.351 | J101: =SUM(J95:J100) -> 14148.762 | K101: =SUM(K95:K100) -> 16608.41
B103: Tangible Non Current Asset Spend | G103: =Schedules!F196*-1 -> -3201.3443 | H103: =Schedules!G196*-1 -> -3534.1285 | I103: =Schedules!H196*-1 -> -3896.2654 | J103: =Schedules!I196*-1 -> -4252.9434 | K103: =Schedules!J196*-1 -> -4643.7073
B104: Intangible Non Current Asset Spend | G104: =Schedules!F200*-1 -> -1920.8066 | H104: =Schedules!G200*-1 -> -2120.4771 | I104: =Schedules!H200*-1 -> -2337.7592 | J104: =Schedules!I200*-1 -> -2551.7661 | K104: =Schedules!J200*-1 -> -2786.2244
B105: Cash Flow from Investing Activities | G105: =SUM(G103:G104) -> -5122.1508 | H105: =SUM(H103:H104) -> -5654.6055 | I105: =SUM(I103:I104) -> -6234.0247 | J105: =SUM(J103:J104) -> -6804.7095 | K105: =SUM(K103:K104) -> -7429.9317
B107: Add/ (Less): Change in Term Loan | G107: =G71-F71 -> 420 | H107: =H71-G71 -> 370 | I107: =I71-H71 -> -130 | J107: =J71-I71 -> -130 | K107: =K71-J71 -> -130
B108: Add/ (Less): Change in Revolver | G108: =G72-F72 -> 0 | H108: =H72-G72 -> 0 | I108: =I72-H72 -> 0 | J108: =J72-I72 -> 0 | K108: =K72-J72 -> 0
B109: Add: Loan Interest Expenses | G109: =G32 -> -653.1672 | H109: =H32 -> -707.0544 | I109: =I32 -> -733.3716 | J109: =J32 -> -733.1688 | K109: =K32 -> -732.446
B110: Add: Revolver Interest Expenses | G110: =G33 -> 0 | H110: =H33 -> 0 | I110: =I33 -> 0 | J110: =J33 -> 0 | K110: =K33 -> 0
B111: Less: Dividend Paid | G111: =Schedules!F265 -> -2124.7735 | H111: =Schedules!G265 -> -2471.9718 | I111: =Schedules!H265 -> -2957.8536 | J111: =Schedules!I265 -> -3279.7245 | K111: =Schedules!J265 -> -3840.8024
B112: Cash Flow from Investing Activities | G112: =SUM(G107:G111) -> -2357.9407 | H112: =SUM(H107:H111) -> -2809.0262 | I112: =SUM(I107:I111) -> -3821.2252 | J112: =SUM(J107:J111) -> -4142.8933 | K112: =SUM(K107:K111) -> -4703.2484
B114: Net Change in cash | G114: =SUM(G112,G105,G101) -> 1204.9414 | H114: =SUM(H112,H105,H101) -> 1871.6962 | I114: =SUM(I112,I105,I101) -> 2419.1015 | J114: =SUM(J112,J105,J101) -> 3201.1596 | K114: =SUM(K112,K105,K101) -> 4475.2295
B115: Opening Cash Balance | G115: =' Balance Sheet'!G9 -> 2181.2644 | H115: =G116 -> 3386.2058 | I115: =H116 -> 5257.902 | J115: =I116 -> 7677.0036 | K115: =J116 -> 10878.163
B116: Closing Cash Balance | G116: =SUM(G114:G115) -> 3386.2058 | H116: =SUM(H114:H115) -> 5257.902 | I116: =SUM(I114:I115) -> 7677.0036 | J116: =SUM(J114:J115) -> 10878.163 | K116: =SUM(K114:K115) -> 15353.393

Sheet Common Size Statement
B2: Mrs Sector Foods
B3: Common Size Statement
F4: Current Case | G4: 1
D8: Actual | G8: Explicit Forecast Period
B9: In INR crores unless started otherwise | D9: 2021 | E9: =D9+1 -> 2022 | F9: =E9+1 -> 2023 | G9: =F9+1 -> 2024 | H9: =G9+1 -> 2025 | I9: =H9+1 -> 2026 | J9: =I9+1 -> 2027 | K9: =J9+1 -> 2028
A11: # | B11: Common Sized Income Statement
B13: Revenue | D13: ='3 Statement Model'!D13/'3 Statement Model'!D$13 -> 1 | E13: ='3 Statement Model'!E13/'3 Statement Model'!E$13 -> 1 | F13: ='3 Statement Model'!F13/'3 Statement Model'!F$13 -> 1 | G13: ='3 Statement Model'!G13/'3 Statement Model'!G$13 -> 1 | H13: ='3 Statement Model'!H13/'3 Statement Model'!H$13 -> 1 | I13: ='3 Statement Model'!I13/'3 Statement Model'!I$13 -> 1 | J13: ='3 Statement Model'!J13/'3 Statement Model'!J$13 -> 1 | K13: ='3 Statement Model'!K13/'3 Statement Model'!K$13 -> 1
B14: Less: Cost of Goods Sold | D14: ='3 Statement Model'!D14/'3 Statement Model'!D$13 -> -0.51200007 | E14: ='3 Statement Model'!E14/'3 Statement Model'!E$13 -> -0.50524035 | F14: ='3 Statement Model'!F14/'3 Statement Model'!F$13 -> -0.48454214 | G14: ='3 Statement Model'!G14/'3 Statement Model'!G$13 -> -0.47112862 | H14: ='3 Statement Model'!H14/'3 Statement Model'!H$13 -> -0.4579466 | I14: ='3 Statement Model'!I14/'3 Statement Model'!I$13 -> -0.44453708 | J14: ='3 Statement Model'!J14/'3 Statement Model'!J$13 -> -0.43135982 | K14: ='3 Statement Model'!K14/'3 Statement Model'!K$13 -> -0.41851846
B15: Gross Profit | D15: ='3 Statement Model'!D15/'3 Statement Model'!D$13 -> 0.48799993 | E15: ='3 Statement Model'!E15/'3 Statement Model'!E$13 -> 0.49475965 | F15: ='3 Statement Model'!F15/'3 Statement Model'!F$13 -> 0.51545786 | G15: ='3 Statement Model'!G15/'3 Statement Model'!G$13 -> 0.52887138 | H15: ='3 Statement Model'!H15/'3 Statement Model'!H$13 -> 0.5420534 | I15: ='3 Statement Model'!I15/'3 Statement Model'!I$13 -> 0.55546292 | J15: ='3 Statement Model'!J15/'3 Statement Model'!J$13 -> 0.56864018 | K15: ='3 Statement Model'!K15/'3 Statement Model'!K$13 -> 0.58148154
B17: Less: SG&A Expenses (Excluding Depreciation & Interest)
B18: Administrative Costs | D18: ='3 Statement Model'!D18/'3 Statement Model'!D$13 -> -0.0060279884 | E18: ='3 Statement Model'!E18/'3 Statement Model'!E$13 -> -0.0059885487 | F18: ='3 Statement Model'!F18/'3 Statement Model'!F$13 -> -0.0059884788 | G18: ='3 Statement Model'!G18/'3 Statement Model'!G$13 -> -0.01 | H18: ='3 Statement Model'!H18/'3 Statement Model'!H$13 -> -0.01 | I18: ='3 Statement Model'!I18/'3 Statement Model'!I$13 -> -0.01 | J18: ='3 Statement Model'!J18/'3 Statement Model'!J$13 -> -0.01 | K18: ='3 Statement Model'!K18/'3 Statement Model'!K$13 -> -0.01
B19: Executive Compensation | D19: ='3 Statement Model'!D19/'3 Statement Model'!D$13 -> -0.054999855 | E19: ='3 Statement Model'!E19/'3 Statement Model'!E$13 -> -0.051999694 | F19: ='3 Statement Model'!F19/'3 Statement Model'!F$13 -> -0.049999983 | G19: ='3 Statement Model'!G19/'3 Statement Model'!G$13 -> -0.053418287 | H19: ='3 Statement Model'!H19/'3 Statement Model'!H$13 -> -0.051637414 | I19: ='3 Statement Model'!I19/'3 Statement Model'!I$13 -> -0.050018859 | J19: ='3 Statement Model'!J19/'3 Statement Model'!J$13 -> -0.048706753 | K19: ='3 Statement Model'!K19/'3 Statement Model'!K$13 -> -0.047475248
B20: Marketing Costs | D20: ='3 Statement Model'!D20/'3 Statement Model'!D$13 -> -0.024999896 | E20: ='3 Statement Model'!E20/'3 Statement Model'!E$13 -> -0.024999767 | F20: ='3 Statement Model'!F20/'3 Statement Model'!F$13 -> -0.024999823 | G20: ='3 Statement Model'!G20/'3 Statement Model'!G$13 -> -0.025 | H20: ='3 Statement Model'!H20/'3 Statement Model'!H$13 -> -0.025 | I20: ='3 Statement Model'!I20/'3 Statement Model'!I$13 -> -0.025 | J20: ='3 Statement Model'!J20/'3 Statement Model'!J$13 -> -0.025 | K20: ='3 Statement Model'!K20/'3 Statement Model'!K$13 -> -0.025
B21: Rent | D21: ='3 Statement Model'!D21/'3 Statement Model'!D$13 -> -0.025713895 | E21: ='3 Statement Model'!E21/'3 Statement Model'!E$13 -> -0.023999687 | F21: ='3 Statement Model'!F21/'3 Statement Model'!F$13 -> -0.021944476 | G21: ='3 Statement Model'!G21/'3 Statement Model'!G$13 -> -0.019897891 | H21: ='3 Statement Model'!H21/'3 Statement Model'!H$13 -> -0.022268574 | I21: ='3 Statement Model'!I21/'3 Statement Model'!I$13 -> -0.020198829 | J21: ='3 Statement Model'!J21/'3 Statement Model'!J$13 -> -0.018504831 | K21: ='3 Statement Model'!K21/'3 Statement Model'!K$13 -> -0.016947666
B22: Retailer Commission | D22: ='3 Statement Model'!D22/'3 Statement Model'!D$13 -> -0.15000004 | E22: ='3 Statement Model'!E22/'3 Statement Model'!E$13 -> -0.14999972 | F22: ='3 Statement Model'!F22/'3 Statement Model'!F$13 -> -0.14999995 | G22: ='3 Statement Model'!G22/'3 Statement Model'!G$13 -> -0.15 | H22: ='3 Statement Model'!H22/'3 Statement Model'!H$13 -> -0.15 | I22: ='3 Statement Model'!I22/'3 Statement Model'!I$13 -> -0.15 | J22: ='3 Statement Model'!J22/'3 Statement Model'!J$13 -> -0.16 | K22: ='3 Statement Model'!K22/'3 Statement Model'!K$13 -> -0.16
B23: Salaries and Wages | D23: ='3 Statement Model'!D23/'3 Statement Model'!D$13 -> -0.10274086 | E23: ='3 Statement Model'!E23/'3 Statement Model'!E$13 -> -0.097999653 | F23: ='3 Statement Model'!F23/'3 Statement Model'!F$13 -> -0.098376075 | G23: ='3 Statement Model'!G23/'3 Statement Model'!G$13 -> -0.09 | H23: ='3 Statement Model'!H23/'3 Statement Model'!H$13 -> -0.09 | I23: ='3 Statement Model'!I23/'3 Statement Model'!I$13 -> -0.09 | J23: ='3 Statement Model'!J23/'3 Statement Model'!J$13 -> -0.09 | K23: ='3 Statement Model'!K23/'3 Statement Model'!K$13 -> -0.09
B24: EBITDA | D24: ='3 Statement Model'!D24/'3 Statement Model'!D$13 -> 0.1235174 | E24: ='3 Statement Model'!E24/'3 Statement Model'!E$13 -> 0.13977258 | F24: ='3 Statement Model'!F24/'3 Statement Model'!F$13 -> 0.16414907 | G24: ='3 Statement Model'!G24/'3 Statement Model'!G$13 -> 0.1805552 | H24: ='3 Statement Model'!H24/'3 Statement Model'!H$13 -> 0.19314741 | I24: ='3 Statement Model'!I24/'3 Statement Model'!I$13 -> 0.21024523 | J24: ='3 Statement Model'!J24/'3 Statement Model'!J$13 -> 0.21642859 | K24: ='3 Statement Model'!K24/'3 Statement Model'!K$13 -> 0.23205863
B26: Less: Depreciation & Amortization
B27: Depreciation | D27: ='3 Statement Model'!D27/'3 Statement Model'!D$13 -> -0.015131059 | E27: ='3 Statement Model'!E27/'3 Statement Model'!E$13 -> -0.013999631 | F27: ='3 Statement Model'!F27/'3 Statement Model'!F$13 -> -0.01349349 | G27: ='3 Statement Model'!G27/'3 Statement Model'!G$13 -> -0.01723506 | H27: ='3 Statement Model'!H27/'3 Statement Model'!H$13 -> -0.020612155 | I27: ='3 Statement Model'!I27/'3 Statement Model'!I$13 -> -0.023696366 | J27: ='3 Statement Model'!J27/'3 Statement Model'!J$13 -> -0.026709043 | K27: ='3 Statement Model'!K27/'3 Statement Model'!K$13 -> -0.0294615
B28: Amortization | D28: ='3 Statement Model'!D28/'3 Statement Model'!D$13 -> -0.0062209834 | E28: ='3 Statement Model'!E28/'3 Statement Model'!E$13 -> -0.0051167413 | F28: ='3 Statement Model'!F28/'3 Statement Model'!F$13 -> -0.0039999716 | G28: ='3 Statement Model'!G28/'3 Statement Model'!G$13 -> -0.0056269264 | H28: ='3 Statement Model'!H28/'3 Statement Model'!H$13 -> -0.007097078 | I28: ='3 Statement Model'!I28/'3 Statement Model'!I$13 -> -0.0084374427 | J28: ='3 Statement Model'!J28/'3 Statement Model'!J$13 -> -0.0097298268 | K28: ='3 Statement Model'!K28/'3 Statement Model'!K$13 -> -0.01091107
B29: EBIT | D29: ='3 Statement Model'!D29/'3 Statement Model'!D$13 -> 0.10216535 | E29: ='3 Statement Model'!E29/'3 Statement Model'!E$13 -> 0.1206562 | F29: ='3 Statement Model'!F29/'3 Statement Model'!F$13 -> 0.14665561 | G29: ='3 Statement Model'!G29/'3 Statement Model'!G$13 -> 0.15769321 | H29: ='3 Statement Model'!H29/'3 Statement Model'!H$13 -> 0.16543818 | I29: ='3 Statement Model'!I29/'3 Statement Model'!I$13 -> 0.17811142 | J29: ='3 Statement Model'!J29/'3 Statement Model'!J$13 -> 0.17998972 | K29: ='3 Statement Model'!K29/'3 Statement Model'!K$13 -> 0.19168606
B31: Less: Total Interest Expenses
B32: Loan Interest Expenses | D32: ='3 Statement Model'!D32/'3 Statement Model'!D$13 -> -0.00711928 | E32: ='3 Statement Model'!E32/'3 Statement Model'!E$13 -> -0.0058561742 | F32: ='3 Statement Model'!F32/'3 Statement Model'!F$13 -> -0.0048007762 | G32: ='3 Statement Model'!G32/'3 Statement Model'!G$13 -> -0.010201452 | H32: ='3 Statement Model'!H32/'3 Statement Model'!H$13 -> -0.010003236 | I32: ='3 Statement Model'!I32/'3 Statement Model'!I$13 -> -0.009411212 | J32: ='3 Statement Model'!J32/'3 Statement Model'!J$13 -> -0.0086195456 | K32: ='3 Statement Model'!K32/'3 Statement Model'!K$13 -> -0.0078864358
B33: Rovolver Interest | D33: ='3 Statement Model'!D33/'3 Statement Model'!D$13 -> 0 | E33: ='3 Statement Model'!E33/'3 Statement Model'!E$13 -> 0 | F33: ='3 Statement Model'!F33/'3 Statement Model'!F$13 -> 0 | G33: ='3 Statement Model'!G33/'3 Statement Model'!G$13 -> 0 | H33: ='3 Statement Model'!H33/'3 Statement Model'!H$13 -> 0 | I33: ='3 Statement Model'!I33/'3 Statement Model'!I$13 -> 0 | J33: ='3 Statement Model'!J33/'3 Statement Model'!J$13 -> 0 | K33: ='3 Statement Model'!K33/'3 Statement Model'!K$13 -> 0
B34: EBT | D34: ='3 Statement Model'!D34/'3 Statement Model'!D$13 -> 0.095046074 | E34: ='3 Statement Model'!E34/'3 Statement Model'!E$13 -> 0.11480003 | F34: ='3 Statement Model'!F34/'3 Statement Model'!F$13 -> 0.14185483 | G34: ='3 Statement Model'!G34/'3 Statement Model'!G$13 -> 0.14749176 | H34: ='3 Statement Model'!H34/'3 Statement Model'!H$13 -> 0.15543494 | I34: ='3 Statement Model'!I34/'3 Statement Model'!I$13 -> 0.16870021 | J34: ='3 Statement Model'!J34/'3 Statement Model'!J$13 -> 0.17137018 | K34: ='3 Statement Model'!K34/'3 Statement Model'!K$13 -> 0.18379962
B36: Less: Taxes | D36: ='3 Statement Model'!D36/'3 Statement Model'!D$13 -> -0.019151784 | E36: ='3 Statement Model'!E36/'3 Statement Model'!E$13 -> -0.023132206 | F36: ='3 Statement Model'!F36/'3 Statement Model'!F$13 -> -0.028583749 | G36: ='3 Statement Model'!G36/'3 Statement Model'!G$13 -> -0.03687294 | H36: ='3 Statement Model'!H36/'3 Statement Model'!H$13 -> -0.038858736 | I36: ='3 Statement Model'!I36/'3 Statement Model'!I$13 -> -0.042175053 | J36: ='3 Statement Model'!J36/'3 Statement Model'!J$13 -> -0.042842544 | K36: ='3 Statement Model'!K36/'3 Statement Model'!K$13 -> -0.045949905
B37: Net Income | D37: ='3 Statement Model'!D37/'3 Statement Model'!D$13 -> 0.07589429 | E37: ='3 Statement Model'!E37/'3 Statement Model'!E$13 -> 0.091667824 | F37: ='3 Statement Model'!F37/'3 Statement Model'!F$13 -> 0.11327109 | G37: ='3 Statement Model'!G37/'3 Statement Model'!G$13 -> 0.11061882 | H37: ='3 Statement Model'!H37/'3 Statement Model'!H$13 -> 0.11657621 | I37: ='3 Statement Model'!I37/'3 Statement Model'!I$13 -> 0.12652516 | J37: ='3 Statement Model'!J37/'3 Statement Model'!J$13 -> 0.12852763 | K37: ='3 Statement Model'!K37/'3 Statement Model'!K$13 -> 0.13784971
A39: # | B39: Common Sized Balance Sheet
B41: Assets
B42: Cash | D42: ='3 Statement Model'!D49/'3 Statement Model'!D$62 -> 0.061225988 | E42: ='3 Statement Model'!E49/'3 Statement Model'!E$62 -> 0.070390974 | F42: ='3 Statement Model'!F49/'3 Statement Model'!F$62 -> 0.070741653 | G42: ='3 Statement Model'!G49/'3 Statement Model'!G$62 -> 0.091450866 | H42: ='3 Statement Model'!H49/'3 Statement Model'!H$62 -> 0.11935231 | I42: ='3 Statement Model'!I49/'3 Statement Model'!I$62 -> 0.14830644 | J42: ='3 Statement Model'!J49/'3 Statement Model'!J$62 -> 0.18078498 | K42: ='3 Statement Model'!K49/'3 Statement Model'!K$62 -> 0.21946478
B43: Inventory | D43: ='3 Statement Model'!D50/'3 Statement Model'!D$62 -> 0.19504339 | E43: ='3 Statement Model'!E50/'3 Statement Model'!E$62 -> 0.18552581 | F43: ='3 Statement Model'!F50/'3 Statement Model'!F$62 -> 0.18137715 | G43: ='3 Statement Model'!G50/'3 Statement Model'!G$62 -> 0.16206047 | H43: ='3 Statement Model'!H50/'3 Statement Model'!H$62 -> 0.14616597 | I43: ='3 Statement Model'!I50/'3 Statement Model'!I$62 -> 0.13312376 | J43: ='3 Statement Model'!J50/'3 Statement Model'!J$62 -> 0.12130169 | K43: ='3 Statement Model'!K50/'3 Statement Model'!K$62 -> 0.11052759
B44: Debtors | D44: ='3 Statement Model'!D51/'3 Statement Model'!D$62 -> 0.22789741 | E44: ='3 Statement Model'!E51/'3 Statement Model'!E$62 -> 0.21677675 | F44: ='3 Statement Model'!F51/'3 Statement Model'!F$62 -> 0.21245125 | G44: ='3 Statement Model'!G51/'3 Statement Model'!G$62 -> 0.19526589 | H44: ='3 Statement Model'!H51/'3 Statement Model'!H$62 -> 0.18118415 | I44: ='3 Statement Model'!I51/'3 Statement Model'!I$62 -> 0.16999508 | J44: ='3 Statement Model'!J51/'3 Statement Model'!J$62 -> 0.15963052 | K44: ='3 Statement Model'!K51/'3 Statement Model'!K$62 -> 0.14991492
B45: Prepaid Expenses | D45: ='3 Statement Model'!D52/'3 Statement Model'!D$62 -> 0.069087332 | E45: ='3 Statement Model'!E52/'3 Statement Model'!E$62 -> 0.06891684 | F45: ='3 Statement Model'!F52/'3 Statement Model'!F$62 -> 0.070927265 | G45: ='3 Statement Model'!G52/'3 Statement Model'!G$62 -> 0.065189898 | H45: ='3 Statement Model'!H52/'3 Statement Model'!H$62 -> 0.060488683 | I45: ='3 Statement Model'!I52/'3 Statement Model'!I$62 -> 0.056753188 | J45: ='3 Statement Model'!J52/'3 Statement Model'!J$62 -> 0.05329296 | K45: ='3 Statement Model'!K52/'3 Statement Model'!K$62 -> 0.050049387
B46: Other Current Assets | D46: ='3 Statement Model'!D53/'3 Statement Model'!D$62 -> 0.0040619935 | E46: ='3 Statement Model'!E53/'3 Statement Model'!E$62 -> 0.004678437 | F46: ='3 Statement Model'!F53/'3 Statement Model'!F$62 -> 0.0049021882 | G46: ='3 Statement Model'!G53/'3 Statement Model'!G$62 -> 0.004505646 | H46: ='3 Statement Model'!H53/'3 Statement Model'!H$62 -> 0.0041807182 | I46: ='3 Statement Model'!I53/'3 Statement Model'!I$62 -> 0.0039225369 | J46: ='3 Statement Model'!J53/'3 Statement Model'!J$62 -> 0.0036833808 | K46: ='3 Statement Model'!K53/'3 Statement Model'!K$62 -> 0.0034591989
B47: Total Current Assets | D47: ='3 Statement Model'!D54/'3 Statement Model'!D$62 -> 0.55731612 | E47: ='3 Statement Model'!E54/'3 Statement Model'!E$62 -> 0.54628881 | F47: ='3 Statement Model'!F54/'3 Statement Model'!F$62 -> 0.54039951 | G47: ='3 Statement Model'!G54/'3 Statement Model'!G$62 -> 0.51847277 | H47: ='3 Statement Model'!H54/'3 Statement Model'!H$62 -> 0.51137184 | I47: ='3 Statement Model'!I54/'3 Statement Model'!I$62 -> 0.51210101 | J47: ='3 Statement Model'!J54/'3 Statement Model'!J$62 -> 0.51869354 | K47: ='3 Statement Model'!K54/'3 Statement Model'!K$62 -> 0.53341587
B49: Net Property, Plant & Equipment | D49: ='3 Statement Model'!D56/'3 Statement Model'!D$62 -> 0.29159893 | E49: ='3 Statement Model'!E56/'3 Statement Model'!E$62 -> 0.29902005 | F49: ='3 Statement Model'!F56/'3 Statement Model'!F$62 -> 0.30781699 | G49: ='3 Statement Model'!G56/'3 Statement Model'!G$62 -> 0.31298647 | H49: ='3 Statement Model'!H56/'3 Statement Model'!H$62 -> 0.31022068 | I49: ='3 Statement Model'!I56/'3 Statement Model'!I$62 -> 0.30360721 | J49: ='3 Statement Model'!J56/'3 Statement Model'!J$62 -> 0.2941105 | K49: ='3 Statement Model'!K56/'3 Statement Model'!K$62 -> 0.28023336
B50: Net Intangible Assets | D50: ='3 Statement Model'!D57/'3 Statement Model'!D$62 -> 0.10404168 | E50: ='3 Statement Model'!E57/'3 Statement Model'!E$62 -> 0.093495527 | F50: ='3 Statement Model'!F57/'3 Statement Model'!F$62 -> 0.092577749 | G50: ='3 Statement Model'!G57/'3 Statement Model'!G$62 -> 0.11923797 | H50: ='3 Statement Model'!H57/'3 Statement Model'!H$62 -> 0.13696791 | I50: ='3 Statement Model'!I57/'3 Statement Model'!I$62 -> 0.14902505 | J50: ='3 Statement Model'!J57/'3 Statement Model'!J$62 -> 0.15685679 | K50: ='3 Statement Model'!K57/'3 Statement Model'!K$62 -> 0.16025576
B51: Goodwill | D51: ='3 Statement Model'!D58/'3 Statement Model'!D$62 -> 0 | E51: ='3 Statement Model'!E58/'3 Statement Model'!E$62 -> 0 | F51: ='3 Statement Model'!F58/'3 Statement Model'!F$62 -> 0 | G51: ='3 Statement Model'!G58/'3 Statement Model'!G$62 -> 0 | H51: ='3 Statement Model'!H58/'3 Statement Model'!H$62 -> 0 | I51: ='3 Statement Model'!I58/'3 Statement Model'!I$62 -> 0 | J51: ='3 Statement Model'!J58/'3 Statement Model'!J$62 -> 0 | K51: ='3 Statement Model'!K58/'3 Statement Model'!K$62 -> 0
B52: Other Non-Current Assets | D52: ='3 Statement Model'!D59/'3 Statement Model'!D$62 -> 0.047043268 | E52: ='3 Statement Model'!E59/'3 Statement Model'!E$62 -> 0.06119562 | F52: ='3 Statement Model'!F59/'3 Statement Model'!F$62 -> 0.059205746 | G52: ='3 Statement Model'!G59/'3 Statement Model'!G$62 -> 0.049302783 | H52: ='3 Statement Model'!H59/'3 Statement Model'!H$62 -> 0.041439577 | I52: ='3 Statement Model'!I59/'3 Statement Model'!I$62 -> 0.035266735 | J52: ='3 Statement Model'!J59/'3 Statement Model'!J$62 -> 0.030339174 | K52: ='3 Statement Model'!K59/'3 Statement Model'!K$62 -> 0.026095008
B53: Total Non-Current Assets | D53: ='3 Statement Model'!D60/'3 Statement Model'!D$62 -> 0.44268388 | E53: ='3 Statement Model'!E60/'3 Statement Model'!E$62 -> 0.45371119 | F53: ='3 Statement Model'!F60/'3 Statement Model'!F$62 -> 0.45960049 | G53: ='3 Statement Model'!G60/'3 Statement Model'!G$62 -> 0.48152723 | H53: ='3 Statement Model'!H60/'3 Statement Model'!H$62 -> 0.48862816 | I53: ='3 Statement Model'!I60/'3 Statement Model'!I$62 -> 0.48789899 | J53: ='3 Statement Model'!J60/'3 Statement Model'!J$62 -> 0.48130646 | K53: ='3 Statement Model'!K60/'3 Statement Model'!K$62 -> 0.46658413
B55: Total Assets | D55: ='3 Statement Model'!D62/'3 Statement Model'!D$62 -> 1 | E55: ='3 Statement Model'!E62/'3 Statement Model'!E$62 -> 1 | F55: ='3 Statement Model'!F62/'3 Statement Model'!F$62 -> 1 | G55: ='3 Statement Model'!G62/'3 Statement Model'!G$62 -> 1 | H55: ='3 Statement Model'!H62/'3 Statement Model'!H$62 -> 1 | I55: ='3 Statement Model'!I62/'3 Statement Model'!I$62 -> 1 | J55: ='3 Statement Model'!J62/'3 Statement Model'!J$62 -> 1 | K55: ='3 Statement Model'!K62/'3 Statement Model'!K$62 -> 1
B58: Liabilities and Shareholders' Equity
B59: Creditors | D59: ='3 Statement Model'!D66/'3 Statement Model'!D$80 -> 0.19522202 | E59: ='3 Statement Model'!E66/'3 Statement Model'!E$80 -> 0.19421121 | F59: ='3 Statement Model'!F66/'3 Statement Model'!F$80 -> 0.196399 | G59: ='3 Statement Model'!G66/'3 Statement Model'!G$80 -> 0.1754825 | H59: ='3 Statement Model'!H66/'3 Statement Model'!H$80 -> 0.15827159 | I59: ='3 Statement Model'!I66/'3 Statement Model'!I$80 -> 0.14414921 | J59: ='3 Statement Model'!J66/'3 Statement Model'!J$80 -> 0.13134803 | K59: ='3 Statement Model'!K66/'3 Statement Model'!K$80 -> 0.1196816
B60: Other Payables | D60: ='3 Statement Model'!D67/'3 Statement Model'!D$80 -> 0.10937203 | E60: ='3 Statement Model'!E67/'3 Statement Model'!E$80 -> 0.11015381 | F60: ='3 Statement Model'!F67/'3 Statement Model'!F$80 -> 0.10843167 | G60: ='3 Statement Model'!G67/'3 Statement Model'!G$80 -> 0.099660544 | H60: ='3 Statement Model'!H67/'3 Statement Model'!H$80 -> 0.092473454 | I60: ='3 Statement Model'!I67/'3 Statement Model'!I$80 -> 0.086762732 | J60: ='3 Statement Model'!J67/'3 Statement Model'!J$80 -> 0.081472829 | K60: ='3 Statement Model'!K67/'3 Statement Model'!K$80 -> 0.076514143
B61: Other Current Liabilities | D61: ='3 Statement Model'!D68/'3 Statement Model'!D$80 -> 0.0078083261 | E61: ='3 Statement Model'!E68/'3 Statement Model'!E$80 -> 0.0077677712 | F61: ='3 Statement Model'!F68/'3 Statement Model'!F$80 -> 0.0084097446 | G61: ='3 Statement Model'!G68/'3 Statement Model'!G$80 -> 0.0077294732 | H61: ='3 Statement Model'!H68/'3 Statement Model'!H$80 -> 0.0071720568 | I61: ='3 Statement Model'!I68/'3 Statement Model'!I$80 -> 0.0067291446 | J61: ='3 Statement Model'!J68/'3 Statement Model'!J$80 -> 0.0063188703 | K61: ='3 Statement Model'!K68/'3 Statement Model'!K$80 -> 0.0059342844
B62: Total Current Liabilities | D62: ='3 Statement Model'!D69/'3 Statement Model'!D$80 -> 0.31240238 | E62: ='3 Statement Model'!E69/'3 Statement Model'!E$80 -> 0.31213279 | F62: ='3 Statement Model'!F69/'3 Statement Model'!F$80 -> 0.31324042 | G62: ='3 Statement Model'!G69/'3 Statement Model'!G$80 -> 0.28287251 | H62: ='3 Statement Model'!H69/'3 Statement Model'!H$80 -> 0.25791711 | I62: ='3 Statement Model'!I69/'3 Statement Model'!I$80 -> 0.23764109 | J62: ='3 Statement Model'!J69/'3 Statement Model'!J$80 -> 0.21913973 | K62: ='3 Statement Model'!K69/'3 Statement Model'!K$80 -> 0.20213003
B64: Senior Term Loan | D64: ='3 Statement Model'!D71/'3 Statement Model'!D$80 -> 0.31158264 | E64: ='3 Statement Model'!E71/'3 Statement Model'!E$80 -> 0.24615928 | F64: ='3 Statement Model'!F71/'3 Statement Model'!F$80 -> 0.20086767 | G64: ='3 Statement Model'!G71/'3 Statement Model'!G$80 -> 0.17861272 | H64: ='3 Statement Model'!H71/'3 Statement Model'!H$80 -> 0.15852498 | I64: ='3 Statement Model'!I71/'3 Statement Model'!I$80 -> 0.13239971 | J64: ='3 Statement Model'!J71/'3 Statement Model'!J$80 -> 0.11174 | K64: ='3 Statement Model'!K71/'3 Statement Model'!K$80 -> 0.094250371
B65: Revolving Credit | D65: ='3 Statement Model'!D72/'3 Statement Model'!D$80 -> 0 | E65: ='3 Statement Model'!E72/'3 Statement Model'!E$80 -> 0 | F65: ='3 Statement Model'!F72/'3 Statement Model'!F$80 -> 0 | G65: ='3 Statement Model'!G72/'3 Statement Model'!G$80 -> 0 | H65: ='3 Statement Model'!H72/'3 Statement Model'!H$80 -> 0 | I65: ='3 Statement Model'!I72/'3 Statement Model'!I$80 -> 0 | J65: ='3 Statement Model'!J72/'3 Statement Model'!J$80 -> 0 | K65: ='3 Statement Model'!K72/'3 Statement Model'!K$80 -> 0
B66: Other Non-Current Liabilities | D66: ='3 Statement Model'!D73/'3 Statement Model'!D$80 -> 0.018703115 | E66: ='3 Statement Model'!E73/'3 Statement Model'!E$80 -> 0.06502978 | F66: ='3 Statement Model'!F73/'3 Statement Model'!F$80 -> 0.029303161 | G66: ='3 Statement Model'!G73/'3 Statement Model'!G$80 -> 0.02440181 | H66: ='3 Statement Model'!H73/'3 Statement Model'!H$80 -> 0.020510012 | I66: ='3 Statement Model'!I73/'3 Statement Model'!I$80 -> 0.017454839 | J66: ='3 Statement Model'!J73/'3 Statement Model'!J$80 -> 0.015016004 | K66: ='3 Statement Model'!K73/'3 Statement Model'!K$80 -> 0.012915406
B67: Total Non-Current Liabilities | D67: ='3 Statement Model'!D74/'3 Statement Model'!D$80 -> 0.33028575 | E67: ='3 Statement Model'!E74/'3 Statement Model'!E$80 -> 0.31118906 | F67: ='3 Statement Model'!F74/'3 Statement Model'!F$80 -> 0.23017083 | G67: ='3 Statement Model'!G74/'3 Statement Model'!G$80 -> 0.20301453 | H67: ='3 Statement Model'!H74/'3 Statement Model'!H$80 -> 0.17903499 | I67: ='3 Statement Model'!I74/'3 Statement Model'!I$80 -> 0.14985455 | J67: ='3 Statement Model'!J74/'3 Statement Model'!J$80 -> 0.126756 | K67: ='3 Statement Model'!K74/'3 Statement Model'!K$80 -> 0.10716578
B69: Equity Shares | D69: ='3 Statement Model'!D76/'3 Statement Model'!D$80 -> 0.040783068 | E69: ='3 Statement Model'!E76/'3 Statement Model'!E$80 -> 0.035266373 | F69: ='3 Statement Model'!F76/'3 Statement Model'!F$80 -> 0.03178286 | G69: ='3 Statement Model'!G76/'3 Statement Model'!G$80 -> 0.026466746 | H69: ='3 Statement Model'!H76/'3 Statement Model'!H$80 -> 0.022245615 | I69: ='3 Statement Model'!I76/'3 Statement Model'!I$80 -> 0.018931907 | J69: ='3 Statement Model'!J76/'3 Statement Model'!J$80 -> 0.016286691 | K69: ='3 Statement Model'!K76/'3 Statement Model'!K$80 -> 0.014008336
B70: Retained Earnings | D70: ='3 Statement Model'!D77/'3 Statement Model'!D$80 -> 0.31652881 | E70: ='3 Statement Model'!E77/'3 Statement Model'!E$80 -> 0.34141178 | F70: ='3 Statement Model'!F77/'3 Statement Model'!F$80 -> 0.42480589 | G70: ='3 Statement Model'!G77/'3 Statement Model'!G$80 -> 0.48764621 | H70: ='3 Statement Model'!H77/'3 Statement Model'!H$80 -> 0.54080229 | I70: ='3 Statement Model'!I77/'3 Statement Model'!I$80 -> 0.59357246 | J70: ='3 Statement Model'!J77/'3 Statement Model'!J$80 -> 0.63781758 | K70: ='3 Statement Model'!K77/'3 Statement Model'!K$80 -> 0.67669586
B71: Total Shareholders' Equity | D71: ='3 Statement Model'!D78/'3 Statement Model'!D$80 -> 0.35731187 | E71: ='3 Statement Model'!E78/'3 Statement Model'!E$80 -> 0.37667815 | F71: ='3 Statement Model'!F78/'3 Statement Model'!F$80 -> 0.45658875 | G71: ='3 Statement Model'!G78/'3 Statement Model'!G$80 -> 0.51411295 | H71: ='3 Statement Model'!H78/'3 Statement Model'!H$80 -> 0.5630479 | I71: ='3 Statement Model'!I78/'3 Statement Model'!I$80 -> 0.61250436 | J71: ='3 Statement Model'!J78/'3 Statement Model'!J$80 -> 0.65410427 | K71: ='3 Statement Model'!K78/'3 Statement Model'!K$80 -> 0.69070419
B73: Total Liabilities and Shareholders' Equity | D73: ='3 Statement Model'!D80/'3 Statement Model'!D$80 -> 1 | E73: ='3 Statement Model'!E80/'3 Statement Model'!E$80 -> 1 | F73: ='3 Statement Model'!F80/'3 Statement Model'!F$80 -> 1 | G73: ='3 Statement Model'!G80/'3 Statement Model'!G$80 -> 1 | H73: ='3 Statement Model'!H80/'3 Statement Model'!H$80 -> 1 | I73: ='3 Statement Model'!I80/'3 Statement Model'!I$80 -> 1 | J73: ='3 Statement Model'!J80/'3 Statement Model'!J$80 -> 1 | K73: ='3 Statement Model'!K80/'3 Statement Model'!K$80 -> 1

Sheet Ratio Analysis
B2: Mrs Sector Foods
B3: Ratio Analysis
F4: Current Case | G4: 1
D8: Actual | G8: Explicit Forecast Period
B9: In INR crores unless started otherwise | D9: 2021 | E9: =D9+1 -> 2022 | F9: =E9+1 -> 2023 | G9: =F9+1 -> 2024 | H9: =G9+1 -> 2025 | I9: =H9+1 -> 2026 | J9: =I9+1 -> 2027 | K9: =J9+1 -> 2028
A11: # | B11: Liquidity Ratio
B13: Current Asset | D13: ='3 Statement Model'!D54 -> 13392.072 | E13: ='3 Statement Model'!E54 -> 15180.553 | F13: ='3 Statement Model'!F54 -> 16662.803 | G13: ='3 Statement Model'!G54 -> 19197.801 | H13: ='3 Statement Model'!H54 -> 22527.783 | I13: ='3 Statement Model'!I54 -> 26508.634 | J13: ='3 Statement Model'!J54 -> 31210.739 | K13: ='3 Statement Model'!K54 -> 37316.891
B14: Current Liabilities | D14: ='3 Statement Model'!D69 -> 7506.898 | E14: ='3 Statement Model'!E69 -> 8673.7056 | F14: ='3 Statement Model'!F69 -> 9658.5272 | G14: ='3 Statement Model'!G69 -> 10474.089 | H14: ='3 Statement Model'!H69 -> 11362.184 | I14: ='3 Statement Model'!I69 -> 12301.363 | J14: ='3 Statement Model'!J69 -> 13186.038 | K14: ='3 Statement Model'!K69 -> 14140.682
B15: Current Ratio | D15: =D13/D14 -> 1.7839689 | E15: =E13/E14 -> 1.7501808 | F15: =F13/F14 -> 1.7251909 | G15: =G13/G14 -> 1.832885 | H15: =H13/H14 -> 1.9826984 | I15: =I13/I14 -> 2.1549346 | J15: =J13/J14 -> 2.3669535 | K15: =K13/K14 -> 2.6389739
B17: Current Asset | D17: ='3 Statement Model'!D54 -> 13392.072 | E17: ='3 Statement Model'!E54 -> 15180.553 | F17: ='3 Statement Model'!F54 -> 16662.803 | G17: ='3 Statement Model'!G54 -> 19197.801 | H17: ='3 Statement Model'!H54 -> 22527.783 | I17: ='3 Statement Model'!I54 -> 26508.634 | J17: ='3 Statement Model'!J54 -> 31210.739 | K17: ='3 Statement Model'!K54 -> 37316.891
B18: Inventory | D18: ='3 Statement Model'!D50 -> 4686.8108 | E18: ='3 Statement Model'!E50 -> 5155.486 | F18: ='3 Statement Model'!F50 -> 5592.6248 | G18: ='3 Statement Model'!G50 -> 6000.7099 | H18: ='3 Statement Model'!H50 -> 6439.141 | I18: ='3 Statement Model'!I50 -> 6891.08 | J18: ='3 Statement Model'!J50 -> 7298.9445 | K18: ='3 Statement Model'!K50 -> 7732.3272
B19: Prepaid Expenses | D19: ='3 Statement Model'!D52 -> 1660.1396 | E19: ='3 Statement Model'!E52 -> 1915.0964 | F19: ='3 Statement Model'!F52 -> 2186.9876 | G19: ='3 Statement Model'!G52 -> 2413.8253 | H19: ='3 Statement Model'!H52 -> 2664.7458 | I19: ='3 Statement Model'!I52 -> 2937.7984 | J19: ='3 Statement Model'!J52 -> 3206.7349 | K19: ='3 Statement Model'!K52 -> 3501.3723
B20: Current Liabilities | D20: ='3 Statement Model'!D69 -> 7506.898 | E20: ='3 Statement Model'!E69 -> 8673.7056 | F20: ='3 Statement Model'!F69 -> 9658.5272 | G20: ='3 Statement Model'!G69 -> 10474.089 | H20: ='3 Statement Model'!H69 -> 11362.184 | I20: ='3 Statement Model'!I69 -> 12301.363 | J20: ='3 Statement Model'!J69 -> 13186.038 | K20: ='3 Statement Model'!K69 -> 14140.682
B21: Quick Ratio (Acid Test) | D21: =(D17-D18-D19)/D20 -> 0.93848644 | E21: =(E17-E18-E19)/E20 -> 0.93500642 | F21: =(F17-F18-F19)/F20 -> 0.91972515 | G21: =(G17-G18-G19)/G20 -> 1.0295182 | H21: =(H17-H18-H19)/H20 -> 1.181454 | I21: =(I17-I18-I19)/I20 -> 1.3559274 | J21: =(J17-J18-J19)/J20 -> 1.570226 | K21: =(K17-K18-K19)/K20 -> 1.8445497
B23: Inventory Days | D23: ='3 Statement Model'!D86 -> 70.599951 | E23: ='3 Statement Model'!E86 -> 70.85727 | F23: ='3 Statement Model'!F86 -> 72.565934 | G23: ='3 Statement Model'!G86 -> 72.609531 | H23: ='3 Statement Model'!H86 -> 72.609531 | I23: ='3 Statement Model'!I86 -> 72.609531 | J23: ='3 Statement Model'!J86 -> 72.609531 | K23: ='3 Statement Model'!K86 -> 72.609531
B24: Debtor Days | D24: ='3 Statement Model'!D85 -> 42.23598 | E24: ='3 Statement Model'!E85 -> 41.830285 | F24: ='3 Statement Model'!F85 -> 41.185189 | G24: ='3 Statement Model'!G85 -> 41.217572 | H24: ='3 Statement Model'!H85 -> 41.217572 | I24: ='3 Statement Model'!I85 -> 41.217572 | J24: ='3 Statement Model'!J85 -> 41.217572 | K24: ='3 Statement Model'!K85 -> 41.217572
B25: Creditor Days | D25: ='3 Statement Model'!D87 -> 70.664609 | E25: ='3 Statement Model'!E87 -> 74.174458 | F25: ='3 Statement Model'!F87 -> 78.575923 | G25: ='3 Statement Model'!G87 -> 78.623131 | H25: ='3 Statement Model'!H87 -> 78.623131 | I25: ='3 Statement Model'!I87 -> 78.623131 | J25: ='3 Statement Model'!J87 -> 78.623131 | K25: ='3 Statement Model'!K87 -> 78.623131
B26: Cash Conversion Days | D26: =D23+D24-D25 -> 42.171321 | E26: =E23+E24-E25 -> 38.513097 | F26: =F23+F24-F25 -> 35.1752 | G26: =G23+G24-G25 -> 35.203972 | H26: =H23+H24-H25 -> 35.203972 | I26: =I23+I24-I25 -> 35.203972 | J26: =J23+J24-J25 -> 35.203972 | K26: =K23+K24-K25 -> 35.203972
A28: # | B28: Leverage Ratio / Solvency Ratio
B30: Total Debt | D30: =SUM('3 Statement Model'!D71:D72) -> 7487.2 | E30: =SUM('3 Statement Model'!E71:E72) -> 6840.4 | F30: =SUM('3 Statement Model'!F71:F72) -> 6193.6 | G30: =SUM('3 Statement Model'!G71:G72) -> 6613.6 | H30: =SUM('3 Statement Model'!H71:H72) -> 6983.6 | I30: =SUM('3 Statement Model'!I71:I72) -> 6853.6 | J30: =SUM('3 Statement Model'!J71:J72) -> 6723.6 | K30: =SUM('3 Statement Model'!K71:K72) -> 6593.6
B31: Total Equity | D31: ='3 Statement Model'!D78 -> 8586.0544 | E31: ='3 Statement Model'!E78 -> 10467.325 | F31: ='3 Statement Model'!F78 -> 14078.562 | G31: ='3 Statement Model'!G78 -> 19036.367 | H31: ='3 Statement Model'!H78 -> 24804.301 | I31: ='3 Statement Model'!I78 -> 31705.96 | J31: ='3 Statement Model'!J78 -> 39358.65 | K31: ='3 Statement Model'!K78 -> 48320.523
B32: Debt to Equity Ratio | D32: =D30/D31 -> 0.8720187 | E32: =E30/E31 -> 0.65350029 | F32: =F30/F31 -> 0.43993128 | G32: =G30/G31 -> 0.34741923 | H32: =H30/H31 -> 0.28154794 | I32: =I30/I31 -> 0.21616125 | J32: =J30/J31 -> 0.17082903 | K32: =K30/K31 -> 0.13645548
B34: Total Debt | D34: =SUM('3 Statement Model'!D71:D72) -> 7487.2 | E34: =SUM('3 Statement Model'!E71:E72) -> 6840.4 | F34: =SUM('3 Statement Model'!F71:F72) -> 6193.6 | G34: =SUM('3 Statement Model'!G71:G72) -> 6613.6 | H34: =SUM('3 Statement Model'!H71:H72) -> 6983.6 | I34: =SUM('3 Statement Model'!I71:I72) -> 6853.6 | J34: =SUM('3 Statement Model'!J71:J72) -> 6723.6 | K34: =SUM('3 Statement Model'!K71:K72) -> 6593.6
B35: Total Asset | D35: ='3 Statement Model'!D62 -> 24029.58 | E35: ='3 Statement Model'!E62 -> 27788.512 | F35: ='3 Statement Model'!F62 -> 30834.23 | G35: ='3 Statement Model'!G62 -> 37027.597 | H35: ='3 Statement Model'!H62 -> 44053.625 | I35: ='3 Statement Model'!I62 -> 51764.464 | J35: ='3 Statement Model'!J62 -> 60171.829 | K35: ='3 Statement Model'!K62 -> 69958.345
B36: Debt to Asset Ratio | D36: =D34/D35 -> 0.31158264 | E36: =E34/E35 -> 0.24615928 | F36: =F34/F35 -> 0.20086767 | G36: =G34/G35 -> 0.17861272 | H36: =H34/H35 -> 0.15852498 | I36: =I34/I35 -> 0.13239971 | J36: =J34/J35 -> 0.11174 | K36: =K34/K35 -> 0.094250371
B38: Total Equity | D38: ='3 Statement Model'!D78 -> 8586.0544 | E38: ='3 Statement Model'!E78 -> 10467.325 | F38: ='3 Statement Model'!F78 -> 14078.562 | G38: ='3 Statement Model'!G78 -> 19036.367 | H38: ='3 Statement Model'!H78 -> 24804.301 | I38: ='3 Statement Model'!I78 -> 31705.96 | J38: ='3 Statement Model'!J78 -> 39358.65 | K38: ='3 Statement Model'!K78 -> 48320.523
B39: Total Asset | D39: ='3 Statement Model'!D62 -> 24029.58 | E39: ='3 Statement Model'!E62 -> 27788.512 | F39: ='3 Statement Model'!F62 -> 30834.23 | G39: ='3 Statement Model'!G62 -> 37027.597 | H39: ='3 Statement Model'!H62 -> 44053.625 | I39: ='3 Statement Model'!I62 -> 51764.464 | J39: ='3 Statement Model'!J62 -> 60171.829 | K39: ='3 Statement Model'!K62 -> 69958.345
B40: Equity To Asset Ratio | D40: =D38/D39 -> 0.35731187 | E40: =E38/E39 -> 0.37667815 | F40: =F38/F39 -> 0.45658875 | G40: =G38/G39 -> 0.51411295 | H40: =H38/H39 -> 0.5630479 | I40: =I38/I39 -> 0.61250436 | J40: =J38/J39 -> 0.65410427 | K40: =K38/K39 -> 0.69070419
A42: # | B42: Profitability Ratio
B44: Gross Profit | D44: ='3 Statement Model'!D15 -> 23094.876 | E44: ='3 Statement Model'!E15 -> 26006.044 | F44: ='3 Statement Model'!F15 -> 29925.221 | G44: ='3 Statement Model'!G15 -> 33861.987 | H44: ='3 Statement Model'!H15 -> 38313.727 | I44: ='3 Statement Model'!I15 -> 43284.619 | J44: ='3 Statement Model'!J15 -> 48367.89 | K44: ='3 Statement Model'!K15 -> 54004.602
B45: Total Sales | D45: ='3 Statement Model'!D13 -> 47325.572 | E45: ='3 Statement Model'!E13 -> 52562.986 | F45: ='3 Statement Model'!F13 -> 58055.612 | G45: ='3 Statement Model'!G13 -> 64026.885 | H45: ='3 Statement Model'!H13 -> 70682.569 | I45: ='3 Statement Model'!I13 -> 77925.308 | J45: ='3 Statement Model'!J13 -> 85058.869 | K45: ='3 Statement Model'!K13 -> 92874.147
B46: Gross Profit Margin | D46: =D44/D45 -> 0.48799993 | E46: =E44/E45 -> 0.49475965 | F46: =F44/F45 -> 0.51545786 | G46: =G44/G45 -> 0.52887138 | H46: =H44/H45 -> 0.5420534 | I46: =I44/I45 -> 0.55546292 | J46: =J44/J45 -> 0.56864018 | K46: =K44/K45 -> 0.58148154
B48: EBITDA | D48: ='3 Statement Model'!D24 -> 5845.5314 | E48: ='3 Statement Model'!E24 -> 7346.864 | F48: ='3 Statement Model'!F24 -> 9529.7748 | G48: ='3 Statement Model'!G24 -> 11560.387 | H48: ='3 Statement Model'!H24 -> 13652.155 | I48: ='3 Statement Model'!I24 -> 16383.425 | J48: ='3 Statement Model'!J24 -> 18409.171 | K48: ='3 Statement Model'!K24 -> 21552.247
B49: Total Sales | D49: ='3 Statement Model'!D13 -> 47325.572 | E49: ='3 Statement Model'!E13 -> 52562.986 | F49: ='3 Statement Model'!F13 -> 58055.612 | G49: ='3 Statement Model'!G13 -> 64026.885 | H49: ='3 Statement Model'!H13 -> 70682.569 | I49: ='3 Statement Model'!I13 -> 77925.308 | J49: ='3 Statement Model'!J13 -> 85058.869 | K49: ='3 Statement Model'!K13 -> 92874.147
B50: EBITDA Margin | D50: =D48/D49 -> 0.1235174 | E50: =E48/E49 -> 0.13977258 | F50: =F48/F49 -> 0.16414907 | G50: =G48/G49 -> 0.1805552 | H50: =H48/H49 -> 0.19314741 | I50: =I48/I49 -> 0.21024523 | J50: =J48/J49 -> 0.21642859 | K50: =K48/K49 -> 0.23205863
B52: EBIT | D52: ='3 Statement Model'!D29 -> 4835.0338 | E52: ='3 Statement Model'!E29 -> 6342.0504 | F52: ='3 Statement Model'!F29 -> 8514.1812 | G52: ='3 Statement Model'!G29 -> 10096.605 | H52: ='3 Statement Model'!H29 -> 11693.596 | I52: ='3 Statement Model'!I29 -> 13879.388 | J52: ='3 Statement Model'!J29 -> 15309.722 | K52: ='3 Statement Model'!K29 -> 17802.679
B53: Total Sales | D53: ='3 Statement Model'!D13 -> 47325.572 | E53: ='3 Statement Model'!E13 -> 52562.986 | F53: ='3 Statement Model'!F13 -> 58055.612 | G53: ='3 Statement Model'!G13 -> 64026.885 | H53: ='3 Statement Model'!H13 -> 70682.569 | I53: ='3 Statement Model'!I13 -> 77925.308 | J53: ='3 Statement Model'!J13 -> 85058.869 | K53: ='3 Statement Model'!K13 -> 92874.147
B54: EBIT Margin | D54: =D52/D53 -> 0.10216535 | E54: =E52/E53 -> 0.1206562 | F54: =F52/F53 -> 0.14665561 | G54: =G52/G53 -> 0.15769321 | H54: =H52/H53 -> 0.16543818 | I54: =I52/I53 -> 0.17811142 | J54: =J52/J53 -> 0.17998972 | K54: =K52/K53 -> 0.19168606
B56: Net Profit | D56: ='3 Statement Model'!D37 -> 3591.7407 | E56: ='3 Statement Model'!E37 -> 4818.3346 | F56: ='3 Statement Model'!F37 -> 6576.0222 | G56: ='3 Statement Model'!G37 -> 7082.5784 | H56: ='3 Statement Model'!H37 -> 8239.9059 | I56: ='3 Statement Model'!I37 -> 9859.512 | J56: ='3 Statement Model'!J37 -> 10932.415 | K56: ='3 Statement Model'!K37 -> 12802.675
B57: Total Sales | D57: ='3 Statement Model'!D13 -> 47325.572 | E57: ='3 Statement Model'!E13 -> 52562.986 | F57: ='3 Statement Model'!F13 -> 58055.612 | G57: ='3 Statement Model'!G13 -> 64026.885 | H57: ='3 Statement Model'!H13 -> 70682.569 | I57: ='3 Statement Model'!I13 -> 77925.308 | J57: ='3 Statement Model'!J13 -> 85058.869 | K57: ='3 Statement Model'!K13 -> 92874.147
B58: Net Profit Margin | D58: =D56/D57 -> 0.07589429 | E58: =E56/E57 -> 0.091667824 | F58: =F56/F57 -> 0.11327109 | G58: =G56/G57 -> 0.11061882 | H58: =H56/H57 -> 0.11657621 | I58: =I56/I57 -> 0.12652516 | J58: =J56/J57 -> 0.12852763 | K58: =K56/K57 -> 0.13784971
B60: Net Profit | D60: ='3 Statement Model'!D37 -> 3591.7407 | E60: ='3 Statement Model'!E37 -> 4818.3346 | F60: ='3 Statement Model'!F37 -> 6576.0222 | G60: ='3 Statement Model'!G37 -> 7082.5784 | H60: ='3 Statement Model'!H37 -> 8239.9059 | I60: ='3 Statement Model'!I37 -> 9859.512 | J60: ='3 Statement Model'!J37 -> 10932.415 | K60: ='3 Statement Model'!K37 -> 12802.675
B61: Total Asset | D61: ='3 Statement Model'!D62 -> 24029.58 | E61: ='3 Statement Model'!E62 -> 27788.512 | F61: ='3 Statement Model'!F62 -> 30834.23 | G61: ='3 Statement Model'!G62 -> 37027.597 | H61: ='3 Statement Model'!H62 -> 44053.625 | I61: ='3 Statement Model'!I62 -> 51764.464 | J61: ='3 Statement Model'!J62 -> 60171.829 | K61: ='3 Statement Model'!K62 -> 69958.345
B62: Return on Asset | D62: =D60/D61 -> 0.14947164 | E62: =E60/E61 -> 0.17339304 | F62: =F60/F61 -> 0.21327019 | G62: =G60/G61 -> 0.19127837 | H62: =H60/H61 -> 0.18704263 | I62: =I60/I61 -> 0.19046874 | J62: =J60/J61 -> 0.1816866 | K62: =K60/K61 -> 0.18300425
B64: Net Profit | D64: ='3 Statement Model'!D37 -> 3591.7407 | E64: ='3 Statement Model'!E37 -> 4818.3346 | F64: ='3 Statement Model'!F37 -> 6576.0222 | G64: ='3 Statement Model'!G37 -> 7082.5784 | H64: ='3 Statement Model'!H37 -> 8239.9059 | I64: ='3 Statement Model'!I37 -> 9859.512 | J64: ='3 Statement Model'!J37 -> 10932.415 | K64: ='3 Statement Model'!K37 -> 12802.675
B65: Total Equity | D65: ='3 Statement Model'!D78 -> 8586.0544 | E65: ='3 Statement Model'!E78 -> 10467.325 | F65: ='3 Statement Model'!F78 -> 14078.562 | G65: ='3 Statement Model'!G78 -> 19036.367 | H65: ='3 Statement Model'!H78 -> 24804.301 | I65: ='3 Statement Model'!I78 -> 31705.96 | J65: ='3 Statement Model'!J78 -> 39358.65 | K65: ='3 Statement Model'!K78 -> 48320.523
B66: Return on Equity | D66: =D64/D65 -> 0.41832261 | E66: =E64/E65 -> 0.46032148 | F66: =F64/F65 -> 0.46709472 | G66: =G64/G65 -> 0.37205514 | H66: =H64/H65 -> 0.33219665 | I66: =I64/I65 -> 0.31096715 | J66: =J64/J65 -> 0.27776397 | K66: =K64/K65 -> 0.26495315
A68: # | B68: Efficiency Ratio
B70: Revenue | D70: ='3 Statement Model'!D$13 -> 47325.572 | E70: ='3 Statement Model'!E13 -> 52562.986 | F70: ='3 Statement Model'!F13 -> 58055.612 | G70: ='3 Statement Model'!G13 -> 64026.885 | H70: ='3 Statement Model'!H13 -> 70682.569 | I70: ='3 Statement Model'!I13 -> 77925.308 | J70: ='3 Statement Model'!J13 -> 85058.869 | K70: ='3 Statement Model'!K13 -> 92874.147
B71: Total Asset | D71: ='3 Statement Model'!D62 -> 24029.58 | E71: ='3 Statement Model'!E62 -> 27788.512 | F71: ='3 Statement Model'!F62 -> 30834.23 | G71: ='3 Statement Model'!G62 -> 37027.597 | H71: ='3 Statement Model'!H62 -> 44053.625 | I71: ='3 Statement Model'!I62 -> 51764.464 | J71: ='3 Statement Model'!J62 -> 60171.829 | K71: ='3 Statement Model'!K62 -> 69958.345
B72: Asset Turnover Ratio | D72: =D70/D71 -> 1.9694714 | E72: =E70/E71 -> 1.8915366 | F72: =F70/F71 -> 1.8828299 | G72: =G70/G71 -> 1.7291666 | H72: =H70/H71 -> 1.6044666 | I72: =I70/I71 -> 1.5053823 | J72: =J70/J71 -> 1.4135995 | K72: =K70/K71 -> 1.3275635
B74: Change in Revenue | D74: - | E74: =E70-D70 -> 5237.414 | F74: =F70-E70 -> 5492.6256 | G74: =G70-F70 -> 5971.2734 | H74: =H70-G70 -> 6655.6842 | I74: =I70-H70 -> 7242.7391 | J74: =J70-I70 -> 7133.5603 | K74: =K70-J70 -> 7815.2781
B75: Change in Asset | D75: - | E75: =E71-D71 -> 3758.9311 | F75: =F71-E71 -> 3045.7185 | G75: =G71-F71 -> 6193.3671 | H75: =H71-G71 -> 7026.0283 | I75: =I71-H71 -> 7710.8383 | J75: =J71-I71 -> 8407.3651 | K75: =K71-J71 -> 9786.5165
B76: Reinvestment Ratio | D76: - | E76: =E74/E75 -> 1.3933253 | F76: =F74/F75 -> 1.8033924 | G76: =G74/G75 -> 0.96414007 | H76: =H74/H75 -> 0.9472897 | I76: =I74/I75 -> 0.93929334 | J76: =J74/J75 -> 0.84848941 | K76: =K74/K75 -> 0.79857609
B78: COGS | D78: ='3 Statement Model'!D14*-1 -> 24230.696 | E78: ='3 Statement Model'!E14*-1 -> 26556.942 | F78: ='3 Statement Model'!F14*-1 -> 28130.39 | G78: ='3 Statement Model'!G14*-1 -> 30164.898 | H78: ='3 Statement Model'!H14*-1 -> 32368.842 | I78: ='3 Statement Model'!I14*-1 -> 34640.689 | J78: ='3 Statement Model'!J14*-1 -> 36690.979 | K78: ='3 Statement Model'!K14*-1 -> 38869.545
B79: Inventory | D79: ='3 Statement Model'!D50 -> 4686.8108 | E79: ='3 Statement Model'!E50 -> 5155.486 | F79: ='3 Statement Model'!F50 -> 5592.6248 | G79: ='3 Statement Model'!G50 -> 6000.7099 | H79: ='3 Statement Model'!H50 -> 6439.141 | I79: ='3 Statement Model'!I50 -> 6891.08 | J79: ='3 Statement Model'!J50 -> 7298.9445 | K79: ='3 Statement Model'!K50 -> 7732.3272
B80: Inventory Turnover Ratio | D80: =D78/D79 -> 5.1699753 | E80: =E78/E79 -> 5.1512004 | F80: =F78/F79 -> 5.0299084 | G80: =G78/G79 -> 5.0268883 | H80: =H78/H79 -> 5.0268883 | I80: =I78/I79 -> 5.0268883 | J80: =J78/J79 -> 5.0268883 | K80: =K78/K79 -> 5.0268883
A82: # | B82: Coverage Ratio
B84: Total Debt | D84: =SUM('3 Statement Model'!D71:D72) -> 7487.2 | E84: =SUM('3 Statement Model'!E71:E72) -> 6840.4 | F84: =SUM('3 Statement Model'!F71:F72) -> 6193.6 | G84: =SUM('3 Statement Model'!G71:G72) -> 6613.6 | H84: =SUM('3 Statement Model'!H71:H72) -> 6983.6 | I84: =SUM('3 Statement Model'!I71:I72) -> 6853.6 | J84: =SUM('3 Statement Model'!J71:J72) -> 6723.6 | K84: =SUM('3 Statement Model'!K71:K72) -> 6593.6
B85: EBITDA | D85: ='3 Statement Model'!D24 -> 5845.5314 | E85: ='3 Statement Model'!E24 -> 7346.864 | F85: ='3 Statement Model'!F24 -> 9529.7748 | G85: ='3 Statement Model'!G24 -> 11560.387 | H85: ='3 Statement Model'!H24 -> 13652.155 | I85: ='3 Statement Model'!I24 -> 16383.425 | J85: ='3 Statement Model'!J24 -> 18409.171 | K85: ='3 Statement Model'!K24 -> 21552.247
B86: Debt to EBITDA Coverage Ratio | D86: =D84/D85 -> 1.2808416 | E86: =E84/E85 -> 0.93106392 | F86: =F84/F85 -> 0.64992092 | G86: =G84/G85 -> 0.57209158 | H86: =H84/H85 -> 0.51153827 | I86: =I84/I85 -> 0.41832524 | J86: =J84/J85 -> 0.365231 | K86: =K84/K85 -> 0.30593562
B88: EBIT | E88: ='3 Statement Model'!E29 -> 6342.0504 | F88: ='3 Statement Model'!F29 -> 8514.1812 | G88: ='3 Statement Model'!G29 -> 10096.605 | H88: ='3 Statement Model'!H29 -> 11693.596 | I88: ='3 Statement Model'!I29 -> 13879.388 | J88: ='3 Statement Model'!J29 -> 15309.722 | K88: ='3 Statement Model'!K29 -> 17802.679
B89: Interest | E89: =SUM('3 Statement Model'!E32:E33)*-1 -> 307.818 | F89: =SUM('3 Statement Model'!F32:F33)*-1 -> 278.712 | G89: =SUM('3 Statement Model'!G32:G33)*-1 -> 653.1672 | H89: =SUM('3 Statement Model'!H32:H33)*-1 -> 707.0544 | I89: =SUM('3 Statement Model'!I32:I33)*-1 -> 733.3716 | J89: =SUM('3 Statement Model'!J32:J33)*-1 -> 733.1688 | K89: =SUM('3 Statement Model'!K32:K33)*-1 -> 732.446
B90: Debt Repayment | E90: ='3 Statement Model'!D71-'3 Statement Model'!E71 -> 646.8 | F90: ='3 Statement Model'!E71-'3 Statement Model'!F71 -> 646.8 | G90: =Schedules!F327 -> 80 | H90: =Schedules!G327 -> 130 | I90: =Schedules!H327 -> 130 | J90: =Schedules!I327 -> 130 | K90: =Schedules!J327 -> 130
B91: Debt to EBITDA Coverage Ratio | E91: =E88/SUM(E89:E90) -> 6.6435479 | F91: =F89/F90 -> 0.43090909 | G91: =G89/G90 -> 8.16459 | H91: =H89/H90 -> 5.43888 | I91: =I89/I90 -> 5.64132 | J91: =J89/J90 -> 5.63976 | K91: =K89/K90 -> 5.6342
B93: EBIT | D93: ='3 Statement Model'!D29 -> 4835.0338 | E93: ='3 Statement Model'!E29 -> 6342.0504 | F93: ='3 Statement Model'!F29 -> 8514.1812 | G93: ='3 Statement Model'!G29 -> 10096.605 | H93: ='3 Statement Model'!H29 -> 11693.596 | I93: ='3 Statement Model'!I29 -> 13879.388 | J93: ='3 Statement Model'!J29 -> 15309.722 | K93: ='3 Statement Model'!K29 -> 17802.679
B94: Interest | D94: =SUM('3 Statement Model'!D32:D33)*-1 -> 336.924 | E94: =SUM('3 Statement Model'!E32:E33)*-1 -> 307.818 | F94: =SUM('3 Statement Model'!F32:F33)*-1 -> 278.712 | G94: =SUM('3 Statement Model'!G32:G33)*-1 -> 653.1672 | H94: =SUM('3 Statement Model'!H32:H33)*-1 -> 707.0544 | I94: =SUM('3 Statement Model'!I32:I33)*-1 -> 733.3716 | J94: =SUM('3 Statement Model'!J32:J33)*-1 -> 733.1688 | K94: =SUM('3 Statement Model'!K32:K33)*-1 -> 732.446
B95: Debt to EBITDA Coverage Ratio | D95: =D93/D94 -> 14.350518 | E95: =E93/E94 -> 20.603247 | F95: =F93/F94 -> 30.548312 | G95: =G93/G94 -> 15.457918 | H95: =H93/H94 -> 16.538467 | I95: =I93/I94 -> 18.92545 | J95: =J93/J94 -> 20.881579 | K95: =K93/K94 -> 24.30579

Sheet DCF Val
B2: Mrs Sector Foods
B3: Common Size Statement
E4: Current Case | F4: 1
F8: Explicit Forecast Period
B9: In INR crores unless started otherwise | E9: ='Common Size Statement'!F9 -> 2023 | F9: =E9+1 -> 2024 | G9: =F9+1 -> 2025 | H9: =G9+1 -> 2026 | I9: =H9+1 -> 2027 | J9: =I9+1 -> 2028
A11: # | B11: Free Cash Flow to Firm
B13: EBITDA | F13: ='3 Statement Model'!G24 -> 11560.387 | G13: ='3 Statement Model'!H24 -> 13652.155 | H13: ='3 Statement Model'!I24 -> 16383.425 | I13: ='3 Statement Model'!J24 -> 18409.171 | J13: ='3 Statement Model'!K24 -> 21552.247
B14: Less: Depreciation | F14: ='3 Statement Model'!G27 -> -1103.5072 | G14: ='3 Statement Model'!H27 -> -1456.9201 | H14: ='3 Statement Model'!I27 -> -1846.5466 | I14: ='3 Statement Model'!J27 -> -2271.841 | J14: ='3 Statement Model'!K27 -> -2736.2117
B15: Less: Amortization | F15: ='3 Statement Model'!G28 -> -360.27457 | G15: ='3 Statement Model'!H28 -> -501.63971 | H15: ='3 Statement Model'!I28 -> -657.49033 | I15: ='3 Statement Model'!J28 -> -827.60806 | J15: ='3 Statement Model'!K28 -> -1013.3564
B16: EBIT | F16: =SUM(F13:F15) -> 10096.605 | G16: =SUM(G13:G15) -> 11693.596 | H16: =SUM(H13:H15) -> 13879.388 | I16: =SUM(I13:I15) -> 15309.722 | J16: =SUM(J13:J15) -> 17802.679
B17: Less: Tax | F17: ='3 Statement Model'!G36 -> -2360.8595 | G17: ='3 Statement Model'!H36 -> -2746.6353 | H17: ='3 Statement Model'!I36 -> -3286.504 | I17: ='3 Statement Model'!J36 -> -3644.1383 | J17: ='3 Statement Model'!K36 -> -4267.5582
B18: EBIT (1-T) | F18: =SUM(F16:F17) -> 7735.7456 | G18: =SUM(G16:G17) -> 8946.9603 | H18: =SUM(H16:H17) -> 10592.884 | I18: =SUM(I16:I17) -> 11665.584 | J18: =SUM(J16:J17) -> 13535.121
B19: Add: Depreciation | F19: =F14*-1 -> 1103.5072 | G19: =G14*-1 -> 1456.9201 | H19: =H14*-1 -> 1846.5466 | I19: =I14*-1 -> 2271.841 | J19: =J14*-1 -> 2736.2117
B20: Add: Amortization | F20: =F15*-1 -> 360.27457 | G20: =G15*-1 -> 501.63971 | H20: =H15*-1 -> 657.49033 | I20: =I15*-1 -> 827.60806 | J20: =J15*-1 -> 1013.3564
B22: Less: Reinvestment
B23: Change in Working Capital | F23: ='3 Statement Model'!G100 -> -514.49445 | G23: ='3 Statement Model'!H100 -> -570.19216 | H23: ='3 Statement Model'!I100 -> -622.56916 | I23: ='3 Statement Model'!J100 -> -616.27047 | J23: ='3 Statement Model'!K100 -> -676.27901
B24: Tangible Non Current Spend | F24: ='3 Statement Model'!G103 -> -3201.3443 | G24: ='3 Statement Model'!H103 -> -3534.1285 | H24: ='3 Statement Model'!I103 -> -3896.2654 | I24: ='3 Statement Model'!J103 -> -4252.9434 | J24: ='3 Statement Model'!K103 -> -4643.7073
B25: Intangible Non Current Spend | F25: ='3 Statement Model'!G104 -> -1920.8066 | G25: ='3 Statement Model'!H104 -> -2120.4771 | H25: ='3 Statement Model'!I104 -> -2337.7592 | I25: ='3 Statement Model'!J104 -> -2551.7661 | J25: ='3 Statement Model'!K104 -> -2786.2244
B26: Free Cash Flow to Firm | F26: =F18+F19+F20+F23+F24+F25 -> 3562.8821 | G26: =G18+G19+G20+G23+G24+G25 -> 4680.7224 | H26: =H18+H19+H20+H23+H24+H25 -> 6240.3267 | I26: =I18+I19+I20+I23+I24+I25 -> 7344.0529 | J26: =J18+J19+J20+J23+J24+J25 -> 9178.4779
B28: Discount Period (Year) | C28: Mid Year Convention? | D28: Yes | F28: =IF(D28="Yes",(F9-E9)/2,F9-E9) -> 0.5 | G28: =F28+1 -> 1.5 | H28: =G28+1 -> 2.5 | I28: =H28+1 -> 3.5 | J28: =I28+1 -> 4.5
B29: Discount Rate (WACC) | C29: =C45 -> 0.11048
B30: Present Value Factor | F30: =1/(1+$C$29)^F28 -> 0.94895284 | G30: =1/(1+$C$29)^G28 -> 0.85454294 | H30: =1/(1+$C$29)^H28 -> 0.76952573 | I30: =1/(1+$C$29)^I28 -> 0.69296676 | J30: =1/(1+$C$29)^J28 -> 0.62402453
B32: Present Value of Free Cash Flow to Firm | F32: =F26*F30 -> 3381.0071 | G32: =G26*G30 -> 3999.8783 | H32: =H26*H30 -> 4802.092 | I32: =I26*I30 -> 5089.1846 | J32: =J26*J30 -> 5727.5954
A34: # | B34: Weighted Average Cost of Capital
B36: Risk Free Rate | C36: 0.0458
B37: ERP | C37: 0.06
B38: Beta | C38: 1.01
B39: Cost of Equity | C39: =C36+(C37)*C38 -> 0.1064
B40: Weight of Equity | C40: 0.7
B42: Cost of Debt | C42: 0.12
B43: Weight of Debt | C43: 0.3
B45: Weighted Average Cost of Capital | C45: =C39*C40+C42*C43 -> 0.11048
A47: # | B47: DCF Calculation - Perpetuity Growth
B49: Perpetuity Growth | C49: 0.04
B50: Terminal Year FCFF x (1+PGR) | C50: =J32*(1+C49) -> 5956.6992
B51: Terminal Value | C51: =C50/(C45-C49) -> 84516.164
B52: Present Value of Terminal Value | C52: =C51*J30 -> 52740.16
B53: Present Value of FCFFs | C53: =SUM(F32:J32) -> 22999.757
B54: Enterprise Value | C54: =SUM(C52:C53) -> 75739.917
B55: Implied Exit Multiple | C55: =C54/J13 -> 3.5142469
B56: Implied EV/EBITDA | C56: =C54/'3 Statement Model'!F24 -> 7.9477132
B57: Less: Debt | C57: =SUM('3 Statement Model'!F71:F72)*-1 -> -6193.6
B58: Less: Cash | C58: ='3 Statement Model'!F49*-1 -> -2181.2644
B59: Equity Value | C59: =C54+C57+C58 -> 67365.052
A61: # | B61: DCF Calculation - Exit Multiple
B63: Exit Multiple | C63: 4
B64: Terminal Year EBITDA | C64: =J13 -> 21552.247
B65: Terminal Value | C65: =C64*C63 -> 86208.987
B66: Present Value of Terminal Value | C66: =C65*J30 -> 53796.523
B67: Present Value of FCFFs | C67: =SUM(F32:J32) -> 22999.757
B68: Enterprise Value | C68: =SUM(C66:C67) -> 76796.28
B69: Implied Exit Multiple | C69: =C68/J13 -> 3.563261
B70: Implied EV/EBITDA | C70: =C68/'3 Statement Model'!F24 -> 8.0585619
B71: Less: Debt | C71: =C57 -> -6193.6
B72: Less: Cash | C72: =C58 -> -2181.2644
B73: Equity Value | C73: =C68+C71+C72 -> 68421.416
A75: # | B75: Sensitivity Analysis - Perpetuity Growth
E77: Perpetuity Growth Rate
D78: =C59 -> 67365.052 | E78: 0.02 | F78: =E78+1% -> 0.03 | G78: =F78+1% -> 0.04 | H78: =G78+1% -> 0.05 | I78: =H78+1% -> 0.06 | J78: =I78+1% -> 0.07
C79: WACC | D79: 0.08 | E79: 94529.585 | F79: 111059.07 | G79: 135853.3 | H79: 177177.02 | I79: 259824.45 | J79: 507766.75
D80: =D79+1% -> 0.09 | E80: 77420.811 | F80: 88388.356 | G80: 103742.92 | H80: 126774.76 | I80: 165161.16 | J80: 241933.97
D81: =D80+1% -> 0.1 | E81: 64865.146 | F81: 72511.267 | G81: 82706.094 | H81: 96978.853 | I81: 118387.99 | J81: 154069.89
D82: 0.1105 | E82: 54900.575 | F82: 60347.83 | G82: 67340.405 | H82: 76644.576 | I82: 89633.567 | J82: 109036.87
D83: =D82+1% -> 0.1205 | E83: 47523.006 | F83: 51584.27 | G83: 56654.542 | H83: 63163.19 | I83: 71823.457 | J83: 83913.533
D84: =D83+1% -> 0.1305 | E84: 41619.653 | F84: 44717.627 | G84: 48500.236 | H84: 53222.624 | I84: 59284.697 | J84: 67350.76
A86: # | B86: Sensitivity Analysis - Exit Multiple
E88: Exit Multiple
C89: WACC | D89: =C73 -> 68421.416 | E89: 2 | F89: =E89+1 -> 3 | G89: =F89+1 -> 4 | H89: =G89+1 -> 5 | I89: =H89+1 -> 6 | J89: =I89+1 -> 7
D90: 0.08 | E90: 46960.742 | F90: 62204.276 | G90: 77447.81 | H90: 92691.343 | I90: 107934.88 | J90: 123178.41
D91: =D90+1% -> 0.09 | E91: 45090.053 | F91: 59714.293 | G91: 74338.533 | H91: 88962.774 | I91: 103587.01 | J91: 118211.25
D92: =D91+1% -> 0.1 | E92: 43305.714 | F92: 57341.136 | G92: 71376.558 | H92: 85411.979 | I92: 99447.401 | J92: 113482.82
D93: 0.1105 | E93: 41519.835 | F93: 54967.876 | G93: 68415.917 | H93: 81863.957 | I93: 95311.998 | J93: 108760.04
D94: =D93+1% -> 0.1205 | E94: 39897.819 | F94: 52814.151 | G94: 65730.482 | H94: 78646.813 | I94: 91563.145 | J94: 104479.48
D95: =D94+1% -> 0.1305 | E95: 38348.432 | F95: 50758.524 | G95: 63168.616 | H95: 75578.708 | I95: 87988.8 | J95: 100398.89

Sheet Client Data >

Sheet  Income Statement
B2: Mrs Sector
B3: Audited Income Statement
B6: In Rs Crores unless stated otherwise | E6: 2021 | F6: 2022 | G6: 2023
B8: Revenue | E8: 47325.572 | F8: 52562.986 | G8: 58055.612
B9: Less: Cost of Goods Sold | E9: -24230.696 | F9: -26556.942 | G9: -28130.39
B10: Gross Profit | E10: =SUM(E8:E9) -> 23094.876 | F10: =SUM(F8:F9) -> 26006.044 | G10: =SUM(G8:G9) -> 29925.221
B12: Less: Selling, General and Admin (SG&A)
B13: Administrative Costs | E13: -285.278 | F13: -314.776 | G13: -347.6648
B14: Depreciation | E14: -716.086 | F14: -735.8624 | G14: -783.3728
B15: Amortization | E15: -294.4116 | F15: -268.9512 | G15: -232.2208
B16: Executive Compensation | E16: -2602.8996 | F16: -2733.2592 | G16: -2902.7796
B17: Loan Interest Expenses | E17: -336.924 | F17: -307.818 | G17: -278.712
B18: Marketing Costs | E18: -1183.1344 | F18: -1314.0624 | G18: -1451.38
B19: Rent | E19: -1216.9248 | F19: -1261.4952 | G19: -1274
B20: Retailer Commission | E20: -7098.8378 | F20: -7884.4332 | G20: -8708.3388
B21: Salaries and Wages | E21: -4862.27 | F21: -5151.1544 | G21: -5711.2832
B22: Total SG&A | E22: =SUM(E13:E21) -> -18596.766 | F22: =SUM(F13:F21) -> -19971.812 | G22: =SUM(G13:G21) -> -21689.752
B24: Pre-Tax Profit | E24: =E10+E22 -> 4498.1098 | F24: =F10+F22 -> 6034.2324 | G24: =G10+G22 -> 8235.4692
B26: Less: Taxes | E26: =E24*-0.2015 -> -906.36913 | F26: =F24*-0.2015 -> -1215.8978 | G26: =G24*-0.2015 -> -1659.447
B27: Net Income | E27: =SUM(E24:E26) -> 3591.7407 | F27: =SUM(F24:F26) -> 4818.3346 | G27: =SUM(G24:G26) -> 6576.0222

Sheet  Balance Sheet
B2: Mrs Sector
B3: Audited Balance Sheet
B6: In Rs Crores unless stated otherwise | E6: 2021 | F6: 2022 | G6: 2023
B8: Assets
B9: Cash | E9: 1471.2348 | F9: 1956.0604 | G9: 2181.2644
B10: Inventory | E10: 4686.8108 | F10: 5155.486 | G10: 5592.6248
B11: Debtors | E11: 5476.2792 | F11: 6023.9032 | G11: 6550.7708
B12: Prepaid Expenses | E12: 1660.1396 | F12: 1915.0964 | G12: 2186.9876
B13: Other Current Assets | E13: 97.608 | F13: 130.0068 | G13: 151.1552
B14: Total Current Assets | E14: =SUM(E9:E13) -> 13392.072 | F14: =SUM(F9:F13) -> 15180.553 | G14: =SUM(G9:G13) -> 16662.803
B16: Net Property, Plant & Equipment | E16: 7007 | F16: 8309.322 | G16: 9491.3
B17: Net Intangible Assets | E17: 2500.078 | F17: 2598.1015 | G17: 2854.5636
B18: Goodwill | E18: 0 | F18: 0 | G18: 0
B19: Other Non-Current Assets | E19: 1130.43 | F19: 1700.5352 | G19: 1825.5636
B20: Total Non-Current Assets | E20: =SUM(E16:E19) -> 10637.508 | F20: =SUM(F16:F19) -> 12607.959 | G20: =SUM(G16:G19) -> 14171.427
B22: Total Assets | E22: =E14+E20 -> 24029.58 | F22: =F14+F20 -> 27788.512 | G22: =G14+G20 -> 30834.23
B25: Liabilities and Shareholders' Equity
B26: Creditors | E26: 4691.1032 | F26: 5396.8404 | G26: 6055.812
B27: Other Payables | E27: 2628.164 | F27: 3061.0104 | G27: 3343.4072
B28: Other Current Liabilities | E28: 187.6308 | F28: 215.8548 | G28: 259.308
B29: Total Current Liabilities | E29: =SUM(E26:E28) -> 7506.898 | F29: =SUM(F26:F28) -> 8673.7056 | G29: =SUM(G26:G28) -> 9658.5272
B31: Senior Term Loan | E31: 7487.2 | F31: 6840.4 | G31: 6193.6
B32: Revolving Credit | E32: 0 | F32: 0 | G32: 0
B33: Other Non-Current Liabilities | E33: 449.428 | F33: 1807.0808 | G33: 903.5404
B34: Total Non-Current Liabilities | E34: =SUM(E31:E33) -> 7936.628 | F34: =SUM(F31:F33) -> 8647.4808 | G34: =SUM(G31:G33) -> 7097.1404
B36: Equity Shares | E36: 980 | F36: 980 | G36: 980
B37: Retained Earnings | E37: 7606.0544 | F37: 9487.3251 | G37: 13098.562
B38: Total Shareholders' Equity | E38: =SUM(E36:E37) -> 8586.0544 | F38: =SUM(F36:F37) -> 10467.325 | G38: =SUM(G36:G37) -> 14078.562
B40: Total Liabilities and Shareholders' Equity | E40: =E29+E34+E38 -> 24029.58 | F40: =F29+F34+F38 -> 27788.512 | G40: =G29+G34+G38 -> 30834.23

Sheet Sheet2
G4: PPT Foundation
G5: Cash Flow
G6: Growth
G7: Valuation Mind Set
G8: Tools
G9: advance finance model
